<mes:GenericData xmlns:com="http://www.sdmx.org/resources/sdmxml/schemas/v2_1/common" xmlns:data="http://www.sdmx.org/resources/sdmxml/schemas/v2_1/data/structurespecific" xmlns:str="http://www.sdmx.org/resources/sdmxml/schemas/v2_1/structure" xmlns:mes="http://www.sdmx.org/resources/sdmxml/schemas/v2_1/message" xmlns:gen="http://www.sdmx.org/resources/sdmxml/schemas/v2_1/data/generic" xmlns:footer="http://www.sdmx.org/resources/sdmxml/schemas/v2_1/message/footer" xmlns:xsi="http://www.w3.org/2001/XMLSchema-instance"><mes:Header><mes:Test>false</mes:Test><mes:Structure structureID="SDG"><com:Structure><URN>urn:sdmx:org.sdmx.infomodel.datastructure.DataStructure=KG_NSC:SDG(1.5)</URN></com:Structure></mes:Structure></mes:Header><mes:DataSet structureRef="SDG"><gen:Obs><gen:ObsKey><gen:Value id="FREQ" value="A"/><gen:Value id="REPORTING_TYPE" value="N"/><gen:Value id="SERIES" value="_L_KG_170301_1A"/><gen:Value id="REF_AREA" value="KG"/><gen:Value id="ACTIVITY" value=""/></gen:ObsKey><gen:ObsValue value="866200.6"/><gen:Attributes><gen:Value id="UNIT_MEASURE" value="PER_1000_USD"/><gen:Value id="TIME_DETAIL" value="2008"/></gen:Attributes></gen:Obs><gen:Obs><gen:ObsKey><gen:Value id="FREQ" value="A"/><gen:Value id="REPORTING_TYPE" value="N"/><gen:Value id="SERIES" value="_L_KG_170301_1A"/><gen:Value id="REF_AREA" value="KG"/><gen:Value id="ACTIVITY" value=""/></gen:ObsKey><gen:ObsValue value="660949.3"/><gen:Attributes><gen:Value id="UNIT_MEASURE" value="PER_1000_USD"/><gen:Value id="TIME_DETAIL" value="2009"/></gen:Attributes></gen:Obs><gen:Obs><gen:ObsKey><gen:Value id="FREQ" value="A"/><gen:Value id="REPORTING_TYPE" value="N"/><gen:Value id="SERIES" value="_L_KG_170301_1A"/><gen:Value id="REF_AREA" value="KG"/><gen:Value id="ACTIVITY" value=""/></gen:ObsKey><gen:ObsValue value="666086.0"/><gen:Attributes><gen:Value id="UNIT_MEASURE" value="PER_1000_USD"/><gen:Value id="TIME_DETAIL" value="2010"/></gen:Attributes></gen:Obs><gen:Obs><gen:ObsKey><gen:Value id="FREQ" value="A"/><gen:Value id="REPORTING_TYPE" value="N"/><gen:Value id="SERIES" value="_L_KG_170301_1A"/><gen:Value id="REF_AREA" value="KG"/><gen:Value id="ACTIVITY" value=""/></gen:ObsKey><gen:ObsValue value="849201.1"/><gen:Attributes><gen:Value id="UNIT_MEASURE" value="PER_1000_USD"/><gen:Value id="TIME_DETAIL" value="2011"/></gen:Attributes></gen:Obs><gen:Obs><gen:ObsKey><gen:Value id="FREQ" value="A"/><gen:Value id="REPORTING_TYPE" value="N"/><gen:Value id="SERIES" value="_L_KG_170301_1A"/><gen:Value id="REF_AREA" value="KG"/><gen:Value id="ACTIVITY" value=""/></gen:ObsKey><gen:ObsValue value="590733.3"/><gen:Attributes><gen:Value id="UNIT_MEASURE" value="PER_1000_USD"/><gen:Value id="TIME_DETAIL" value="2012"/></gen:Attributes></gen:Obs><gen:Obs><gen:ObsKey><gen:Value id="FREQ" value="A"/><gen:Value id="REPORTING_TYPE" value="N"/><gen:Value id="SERIES" value="_L_KG_170301_1A"/><gen:Value id="REF_AREA" value="KG"/><gen:Value id="ACTIVITY" value=""/></gen:ObsKey><gen:ObsValue value="964507.1"/><gen:Attributes><gen:Value id="UNIT_MEASURE" value="PER_1000_USD"/><gen:Value id="TIME_DETAIL" value="2013"/></gen:Attributes></gen:Obs><gen:Obs><gen:ObsKey><gen:Value id="FREQ" value="A"/><gen:Value id="REPORTING_TYPE" value="N"/><gen:Value id="SERIES" value="_L_KG_170301_1A"/><gen:Value id="REF_AREA" value="KG"/><gen:Value id="ACTIVITY" value=""/></gen:ObsKey><gen:ObsValue value="727091.2"/><gen:Attributes><gen:Value id="UNIT_MEASURE" value="PER_1000_USD"/><gen:Value id="TIME_DETAIL" value="2014"/></gen:Attributes></gen:Obs><gen:Obs><gen:ObsKey><gen:Value id="FREQ" value="A"/><gen:Value id="REPORTING_TYPE" value="N"/><gen:Value id="SERIES" value="_L_KG_170301_1A"/><gen:Value id="REF_AREA" value="KG"/><gen:Value id="ACTIVITY" value=""/></gen:ObsKey><gen:ObsValue value="1573243.7"/><gen:Attributes><gen:Value id="UNIT_MEASURE" value="PER_1000_USD"/><gen:Value id="TIME_DETAIL" value="2015"/></gen:Attributes></gen:Obs><gen:Obs><gen:ObsKey><gen:Value id="FREQ" value="A"/><gen:Value id="REPORTING_TYPE" value="N"/><gen:Value id="SERIES" value="_L_KG_170301_1A"/><gen:Value id="REF_AREA" value="KG"/><gen:Value id="ACTIVITY" value=""/></gen:ObsKey><gen:ObsValue value="813960.7"/><gen:Attributes><gen:Value id="UNIT_MEASURE" value="PER_1000_USD"/><gen:Value id="TIME_DETAIL" value="2016"/></gen:Attributes></gen:Obs><gen:Obs><gen:ObsKey><gen:Value id="FREQ" value="A"/><gen:Value id="REPORTING_TYPE" value="N"/><gen:Value id="SERIES" value="_L_KG_170301_1A"/><gen:Value id="REF_AREA" value="KG"/><gen:Value id="ACTIVITY" value=""/></gen:ObsKey><gen:ObsValue value="616793.1"/><gen:Attributes><gen:Value id="UNIT_MEASURE" value="PER_1000_USD"/><gen:Value id="TIME_DETAIL" value="2017"/></gen:Attributes></gen:Obs><gen:Obs><gen:ObsKey><gen:Value id="FREQ" value="A"/><gen:Value id="REPORTING_TYPE" value="N"/><gen:Value id="SERIES" value="_L_KG_170301_1A"/><gen:Value id="REF_AREA" value="KG"/><gen:Value id="ACTIVITY" value=""/></gen:ObsKey><gen:ObsValue value="851743.6"/><gen:Attributes><gen:Value id="UNIT_MEASURE" value="PER_1000_USD"/><gen:Value id="TIME_DETAIL" value="2018"/></gen:Attributes></gen:Obs><gen:Obs><gen:ObsKey><gen:Value id="FREQ" value="A"/><gen:Value id="REPORTING_TYPE" value="N"/><gen:Value id="SERIES" value="_L_KG_170301_1A"/><gen:Value id="REF_AREA" value="KG"/><gen:Value id="ACTIVITY" value="ISIC4_A"/></gen:ObsKey><gen:ObsValue value="583.5904"/><gen:Attributes><gen:Value id="UNIT_MEASURE" value="PER_1000_USD"/><gen:Value id="TIME_DETAIL" value="2008"/></gen:Attributes></gen:Obs><gen:Obs><gen:ObsKey><gen:Value id="FREQ" value="A"/><gen:Value id="REPORTING_TYPE" value="N"/><gen:Value id="SERIES" value="_L_KG_170301_1A"/><gen:Value id="REF_AREA" value="KG"/><gen:Value id="ACTIVITY" value="ISIC4_A"/></gen:ObsKey><gen:ObsValue value="17.6"/><gen:Attributes><gen:Value id="UNIT_MEASURE" value="PER_1000_USD"/><gen:Value id="TIME_DETAIL" value="2009"/></gen:Attributes></gen:Obs><gen:Obs><gen:ObsKey><gen:Value id="FREQ" value="A"/><gen:Value id="REPORTING_TYPE" value="N"/><gen:Value id="SERIES" value="_L_KG_170301_1A"/><gen:Value id="REF_AREA" value="KG"/><gen:Value id="ACTIVITY" value="ISIC4_A"/></gen:ObsKey><gen:ObsValue value="2.7"/><gen:Attributes><gen:Value id="UNIT_MEASURE" value="PER_1000_USD"/><gen:Value id="TIME_DETAIL" value="2010"/></gen:Attributes></gen:Obs><gen:Obs><gen:ObsKey><gen:Value id="FREQ" value="A"/><gen:Value id="REPORTING_TYPE" value="N"/><gen:Value id="SERIES" value="_L_KG_170301_1A"/><gen:Value id="REF_AREA" value="KG"/><gen:Value id="ACTIVITY" value="ISIC4_A"/></gen:ObsKey><gen:ObsValue value="3.5"/><gen:Attributes><gen:Value id="UNIT_MEASURE" value="PER_1000_USD"/><gen:Value id="TIME_DETAIL" value="2011"/></gen:Attributes></gen:Obs><gen:Obs><gen:ObsKey><gen:Value id="FREQ" value="A"/><gen:Value id="REPORTING_TYPE" value="N"/><gen:Value id="SERIES" value="_L_KG_170301_1A"/><gen:Value id="REF_AREA" value="KG"/><gen:Value id="ACTIVITY" value="ISIC4_A"/></gen:ObsKey><gen:ObsValue value="2045.7"/><gen:Attributes><gen:Value id="UNIT_MEASURE" value="PER_1000_USD"/><gen:Value id="TIME_DETAIL" value="2012"/></gen:Attributes></gen:Obs><gen:Obs><gen:ObsKey><gen:Value id="FREQ" value="A"/><gen:Value id="REPORTING_TYPE" value="N"/><gen:Value id="SERIES" value="_L_KG_170301_1A"/><gen:Value id="REF_AREA" value="KG"/><gen:Value id="ACTIVITY" value="ISIC4_A"/></gen:ObsKey><gen:ObsValue value="345.0"/><gen:Attributes><gen:Value id="UNIT_MEASURE" value="PER_1000_USD"/><gen:Value id="TIME_DETAIL" value="2013"/></gen:Attributes></gen:Obs><gen:Obs><gen:ObsKey><gen:Value id="FREQ" value="A"/><gen:Value id="REPORTING_TYPE" value="N"/><gen:Value id="SERIES" value="_L_KG_170301_1A"/><gen:Value id="REF_AREA" value="KG"/><gen:Value id="ACTIVITY" value="ISIC4_A"/></gen:ObsKey><gen:ObsValue value="316.2"/><gen:Attributes><gen:Value id="UNIT_MEASURE" value="PER_1000_USD"/><gen:Value id="TIME_DETAIL" value="2015"/></gen:Attributes></gen:Obs><gen:Obs><gen:ObsKey><gen:Value id="FREQ" value="A"/><gen:Value id="REPORTING_TYPE" value="N"/><gen:Value id="SERIES" value="_L_KG_170301_1A"/><gen:Value id="REF_AREA" value="KG"/><gen:Value id="ACTIVITY" value="ISIC4_A"/></gen:ObsKey><gen:ObsValue value="210.9"/><gen:Attributes><gen:Value id="UNIT_MEASURE" value="PER_1000_USD"/><gen:Value id="TIME_DETAIL" value="2016"/></gen:Attributes></gen:Obs><gen:Obs><gen:ObsKey><gen:Value id="FREQ" value="A"/><gen:Value id="REPORTING_TYPE" value="N"/><gen:Value id="SERIES" value="_L_KG_170301_1A"/><gen:Value id="REF_AREA" value="KG"/><gen:Value id="ACTIVITY" value="ISIC4_A"/></gen:ObsKey><gen:ObsValue value="21.8"/><gen:Attributes><gen:Value id="UNIT_MEASURE" value="PER_1000_USD"/><gen:Value id="TIME_DETAIL" value="2017"/></gen:Attributes></gen:Obs><gen:Obs><gen:ObsKey><gen:Value id="FREQ" value="A"/><gen:Value id="REPORTING_TYPE" value="N"/><gen:Value id="SERIES" value="_L_KG_170301_1A"/><gen:Value id="REF_AREA" value="KG"/><gen:Value id="ACTIVITY" value="ISIC4_A"/></gen:ObsKey><gen:ObsValue value="2327.6"/><gen:Attributes><gen:Value id="UNIT_MEASURE" value="PER_1000_USD"/><gen:Value id="TIME_DETAIL" value="2018"/></gen:Attributes></gen:Obs><gen:Obs><gen:ObsKey><gen:Value id="FREQ" value="A"/><gen:Value id="REPORTING_TYPE" value="N"/><gen:Value id="SERIES" value="_L_KG_170301_1A"/><gen:Value id="REF_AREA" value="KG"/><gen:Value id="ACTIVITY" value="ISIC4_B"/></gen:ObsKey><gen:ObsValue value="7500.0"/><gen:Attributes><gen:Value id="UNIT_MEASURE" value="PER_1000_USD"/><gen:Value id="TIME_DETAIL" value="2008"/></gen:Attributes></gen:Obs><gen:Obs><gen:ObsKey><gen:Value id="FREQ" value="A"/><gen:Value id="REPORTING_TYPE" value="N"/><gen:Value id="SERIES" value="_L_KG_170301_1A"/><gen:Value id="REF_AREA" value="KG"/><gen:Value id="ACTIVITY" value="ISIC4_B"/></gen:ObsKey><gen:ObsValue value="6375.7"/><gen:Attributes><gen:Value id="UNIT_MEASURE" value="PER_1000_USD"/><gen:Value id="TIME_DETAIL" value="2009"/></gen:Attributes></gen:Obs><gen:Obs><gen:ObsKey><gen:Value id="FREQ" value="A"/><gen:Value id="REPORTING_TYPE" value="N"/><gen:Value id="SERIES" value="_L_KG_170301_1A"/><gen:Value id="REF_AREA" value="KG"/><gen:Value id="ACTIVITY" value="ISIC4_B"/></gen:ObsKey><gen:ObsValue value="1028.4"/><gen:Attributes><gen:Value id="UNIT_MEASURE" value="PER_1000_USD"/><gen:Value id="TIME_DETAIL" value="2010"/></gen:Attributes></gen:Obs><gen:Obs><gen:ObsKey><gen:Value id="FREQ" value="A"/><gen:Value id="REPORTING_TYPE" value="N"/><gen:Value id="SERIES" value="_L_KG_170301_1A"/><gen:Value id="REF_AREA" value="KG"/><gen:Value id="ACTIVITY" value="ISIC4_B"/></gen:ObsKey><gen:ObsValue value="26460.8"/><gen:Attributes><gen:Value id="UNIT_MEASURE" value="PER_1000_USD"/><gen:Value id="TIME_DETAIL" value="2011"/></gen:Attributes></gen:Obs><gen:Obs><gen:ObsKey><gen:Value id="FREQ" value="A"/><gen:Value id="REPORTING_TYPE" value="N"/><gen:Value id="SERIES" value="_L_KG_170301_1A"/><gen:Value id="REF_AREA" value="KG"/><gen:Value id="ACTIVITY" value="ISIC4_B"/></gen:ObsKey><gen:ObsValue value="25677.7"/><gen:Attributes><gen:Value id="UNIT_MEASURE" value="PER_1000_USD"/><gen:Value id="TIME_DETAIL" value="2012"/></gen:Attributes></gen:Obs><gen:Obs><gen:ObsKey><gen:Value id="FREQ" value="A"/><gen:Value id="REPORTING_TYPE" value="N"/><gen:Value id="SERIES" value="_L_KG_170301_1A"/><gen:Value id="REF_AREA" value="KG"/><gen:Value id="ACTIVITY" value="ISIC4_B"/></gen:ObsKey><gen:ObsValue value="23151.8"/><gen:Attributes><gen:Value id="UNIT_MEASURE" value="PER_1000_USD"/><gen:Value id="TIME_DETAIL" value="2013"/></gen:Attributes></gen:Obs><gen:Obs><gen:ObsKey><gen:Value id="FREQ" value="A"/><gen:Value id="REPORTING_TYPE" value="N"/><gen:Value id="SERIES" value="_L_KG_170301_1A"/><gen:Value id="REF_AREA" value="KG"/><gen:Value id="ACTIVITY" value="ISIC4_B"/></gen:ObsKey><gen:ObsValue value="74973.3"/><gen:Attributes><gen:Value id="UNIT_MEASURE" value="PER_1000_USD"/><gen:Value id="TIME_DETAIL" value="2014"/></gen:Attributes></gen:Obs><gen:Obs><gen:ObsKey><gen:Value id="FREQ" value="A"/><gen:Value id="REPORTING_TYPE" value="N"/><gen:Value id="SERIES" value="_L_KG_170301_1A"/><gen:Value id="REF_AREA" value="KG"/><gen:Value id="ACTIVITY" value="ISIC4_B"/></gen:ObsKey><gen:ObsValue value="14727.5"/><gen:Attributes><gen:Value id="UNIT_MEASURE" value="PER_1000_USD"/><gen:Value id="TIME_DETAIL" value="2015"/></gen:Attributes></gen:Obs><gen:Obs><gen:ObsKey><gen:Value id="FREQ" value="A"/><gen:Value id="REPORTING_TYPE" value="N"/><gen:Value id="SERIES" value="_L_KG_170301_1A"/><gen:Value id="REF_AREA" value="KG"/><gen:Value id="ACTIVITY" value="ISIC4_B"/></gen:ObsKey><gen:ObsValue value="54302.3"/><gen:Attributes><gen:Value id="UNIT_MEASURE" value="PER_1000_USD"/><gen:Value id="TIME_DETAIL" value="2016"/></gen:Attributes></gen:Obs><gen:Obs><gen:ObsKey><gen:Value id="FREQ" value="A"/><gen:Value id="REPORTING_TYPE" value="N"/><gen:Value id="SERIES" value="_L_KG_170301_1A"/><gen:Value id="REF_AREA" value="KG"/><gen:Value id="ACTIVITY" value="ISIC4_B"/></gen:ObsKey><gen:ObsValue value="80995.2"/><gen:Attributes><gen:Value id="UNIT_MEASURE" value="PER_1000_USD"/><gen:Value id="TIME_DETAIL" value="2017"/></gen:Attributes></gen:Obs><gen:Obs><gen:ObsKey><gen:Value id="FREQ" value="A"/><gen:Value id="REPORTING_TYPE" value="N"/><gen:Value id="SERIES" value="_L_KG_170301_1A"/><gen:Value id="REF_AREA" value="KG"/><gen:Value id="ACTIVITY" value="ISIC4_B"/></gen:ObsKey><gen:ObsValue value="91845.7"/><gen:Attributes><gen:Value id="UNIT_MEASURE" value="PER_1000_USD"/><gen:Value id="TIME_DETAIL" value="2018"/></gen:Attributes></gen:Obs><gen:Obs><gen:ObsKey><gen:Value id="FREQ" value="A"/><gen:Value id="REPORTING_TYPE" value="N"/><gen:Value id="SERIES" value="_L_KG_170301_1A"/><gen:Value id="REF_AREA" value="KG"/><gen:Value id="ACTIVITY" value="ISIC4_C"/></gen:ObsKey><gen:ObsValue value="237437.7"/><gen:Attributes><gen:Value id="UNIT_MEASURE" value="PER_1000_USD"/><gen:Value id="TIME_DETAIL" value="2008"/></gen:Attributes></gen:Obs><gen:Obs><gen:ObsKey><gen:Value id="FREQ" value="A"/><gen:Value id="REPORTING_TYPE" value="N"/><gen:Value id="SERIES" value="_L_KG_170301_1A"/><gen:Value id="REF_AREA" value="KG"/><gen:Value id="ACTIVITY" value="ISIC4_C"/></gen:ObsKey><gen:ObsValue value="153569.3"/><gen:Attributes><gen:Value id="UNIT_MEASURE" value="PER_1000_USD"/><gen:Value id="TIME_DETAIL" value="2009"/></gen:Attributes></gen:Obs><gen:Obs><gen:ObsKey><gen:Value id="FREQ" value="A"/><gen:Value id="REPORTING_TYPE" value="N"/><gen:Value id="SERIES" value="_L_KG_170301_1A"/><gen:Value id="REF_AREA" value="KG"/><gen:Value id="ACTIVITY" value="ISIC4_C"/></gen:ObsKey><gen:ObsValue value="331386.7"/><gen:Attributes><gen:Value id="UNIT_MEASURE" value="PER_1000_USD"/><gen:Value id="TIME_DETAIL" value="2010"/></gen:Attributes></gen:Obs><gen:Obs><gen:ObsKey><gen:Value id="FREQ" value="A"/><gen:Value id="REPORTING_TYPE" value="N"/><gen:Value id="SERIES" value="_L_KG_170301_1A"/><gen:Value id="REF_AREA" value="KG"/><gen:Value id="ACTIVITY" value="ISIC4_C"/></gen:ObsKey><gen:ObsValue value="489551.4"/><gen:Attributes><gen:Value id="UNIT_MEASURE" value="PER_1000_USD"/><gen:Value id="TIME_DETAIL" value="2011"/></gen:Attributes></gen:Obs><gen:Obs><gen:ObsKey><gen:Value id="FREQ" value="A"/><gen:Value id="REPORTING_TYPE" value="N"/><gen:Value id="SERIES" value="_L_KG_170301_1A"/><gen:Value id="REF_AREA" value="KG"/><gen:Value id="ACTIVITY" value="ISIC4_C"/></gen:ObsKey><gen:ObsValue value="257259.1"/><gen:Attributes><gen:Value id="UNIT_MEASURE" value="PER_1000_USD"/><gen:Value id="TIME_DETAIL" value="2012"/></gen:Attributes></gen:Obs><gen:Obs><gen:ObsKey><gen:Value id="FREQ" value="A"/><gen:Value id="REPORTING_TYPE" value="N"/><gen:Value id="SERIES" value="_L_KG_170301_1A"/><gen:Value id="REF_AREA" value="KG"/><gen:Value id="ACTIVITY" value="ISIC4_C"/></gen:ObsKey><gen:ObsValue value="317742.6"/><gen:Attributes><gen:Value id="UNIT_MEASURE" value="PER_1000_USD"/><gen:Value id="TIME_DETAIL" value="2013"/></gen:Attributes></gen:Obs><gen:Obs><gen:ObsKey><gen:Value id="FREQ" value="A"/><gen:Value id="REPORTING_TYPE" value="N"/><gen:Value id="SERIES" value="_L_KG_170301_1A"/><gen:Value id="REF_AREA" value="KG"/><gen:Value id="ACTIVITY" value="ISIC4_C"/></gen:ObsKey><gen:ObsValue value="271250.0"/><gen:Attributes><gen:Value id="UNIT_MEASURE" value="PER_1000_USD"/><gen:Value id="TIME_DETAIL" value="2014"/></gen:Attributes></gen:Obs><gen:Obs><gen:ObsKey><gen:Value id="FREQ" value="A"/><gen:Value id="REPORTING_TYPE" value="N"/><gen:Value id="SERIES" value="_L_KG_170301_1A"/><gen:Value id="REF_AREA" value="KG"/><gen:Value id="ACTIVITY" value="ISIC4_C"/></gen:ObsKey><gen:ObsValue value="564715.3"/><gen:Attributes><gen:Value id="UNIT_MEASURE" value="PER_1000_USD"/><gen:Value id="TIME_DETAIL" value="2015"/></gen:Attributes></gen:Obs><gen:Obs><gen:ObsKey><gen:Value id="FREQ" value="A"/><gen:Value id="REPORTING_TYPE" value="N"/><gen:Value id="SERIES" value="_L_KG_170301_1A"/><gen:Value id="REF_AREA" value="KG"/><gen:Value id="ACTIVITY" value="ISIC4_C"/></gen:ObsKey><gen:ObsValue value="251234.3"/><gen:Attributes><gen:Value id="UNIT_MEASURE" value="PER_1000_USD"/><gen:Value id="TIME_DETAIL" value="2016"/></gen:Attributes></gen:Obs><gen:Obs><gen:ObsKey><gen:Value id="FREQ" value="A"/><gen:Value id="REPORTING_TYPE" value="N"/><gen:Value id="SERIES" value="_L_KG_170301_1A"/><gen:Value id="REF_AREA" value="KG"/><gen:Value id="ACTIVITY" value="ISIC4_C"/></gen:ObsKey><gen:ObsValue value="186333.7"/><gen:Attributes><gen:Value id="UNIT_MEASURE" value="PER_1000_USD"/><gen:Value id="TIME_DETAIL" value="2017"/></gen:Attributes></gen:Obs><gen:Obs><gen:ObsKey><gen:Value id="FREQ" value="A"/><gen:Value id="REPORTING_TYPE" value="N"/><gen:Value id="SERIES" value="_L_KG_170301_1A"/><gen:Value id="REF_AREA" value="KG"/><gen:Value id="ACTIVITY" value="ISIC4_C"/></gen:ObsKey><gen:ObsValue value="376441.7"/><gen:Attributes><gen:Value id="UNIT_MEASURE" value="PER_1000_USD"/><gen:Value id="TIME_DETAIL" value="2018"/></gen:Attributes></gen:Obs><gen:Obs><gen:ObsKey><gen:Value id="FREQ" value="A"/><gen:Value id="REPORTING_TYPE" value="N"/><gen:Value id="SERIES" value="_L_KG_170301_1A"/><gen:Value id="REF_AREA" value="KG"/><gen:Value id="ACTIVITY" value="ISIC4_D"/></gen:ObsKey><gen:ObsValue value="20.5"/><gen:Attributes><gen:Value id="UNIT_MEASURE" value="PER_1000_USD"/><gen:Value id="TIME_DETAIL" value="2010"/></gen:Attributes></gen:Obs><gen:Obs><gen:ObsKey><gen:Value id="FREQ" value="A"/><gen:Value id="REPORTING_TYPE" value="N"/><gen:Value id="SERIES" value="_L_KG_170301_1A"/><gen:Value id="REF_AREA" value="KG"/><gen:Value id="ACTIVITY" value="ISIC4_D"/></gen:ObsKey><gen:ObsValue value="15.1"/><gen:Attributes><gen:Value id="UNIT_MEASURE" value="PER_1000_USD"/><gen:Value id="TIME_DETAIL" value="2012"/></gen:Attributes></gen:Obs><gen:Obs><gen:ObsKey><gen:Value id="FREQ" value="A"/><gen:Value id="REPORTING_TYPE" value="N"/><gen:Value id="SERIES" value="_L_KG_170301_1A"/><gen:Value id="REF_AREA" value="KG"/><gen:Value id="ACTIVITY" value="ISIC4_D"/></gen:ObsKey><gen:ObsValue value="16200.5"/><gen:Attributes><gen:Value id="UNIT_MEASURE" value="PER_1000_USD"/><gen:Value id="TIME_DETAIL" value="2013"/></gen:Attributes></gen:Obs><gen:Obs><gen:ObsKey><gen:Value id="FREQ" value="A"/><gen:Value id="REPORTING_TYPE" value="N"/><gen:Value id="SERIES" value="_L_KG_170301_1A"/><gen:Value id="REF_AREA" value="KG"/><gen:Value id="ACTIVITY" value="ISIC4_D"/></gen:ObsKey><gen:ObsValue value="43580.9"/><gen:Attributes><gen:Value id="UNIT_MEASURE" value="PER_1000_USD"/><gen:Value id="TIME_DETAIL" value="2014"/></gen:Attributes></gen:Obs><gen:Obs><gen:ObsKey><gen:Value id="FREQ" value="A"/><gen:Value id="REPORTING_TYPE" value="N"/><gen:Value id="SERIES" value="_L_KG_170301_1A"/><gen:Value id="REF_AREA" value="KG"/><gen:Value id="ACTIVITY" value="ISIC4_D"/></gen:ObsKey><gen:ObsValue value="136704.8"/><gen:Attributes><gen:Value id="UNIT_MEASURE" value="PER_1000_USD"/><gen:Value id="TIME_DETAIL" value="2015"/></gen:Attributes></gen:Obs><gen:Obs><gen:ObsKey><gen:Value id="FREQ" value="A"/><gen:Value id="REPORTING_TYPE" value="N"/><gen:Value id="SERIES" value="_L_KG_170301_1A"/><gen:Value id="REF_AREA" value="KG"/><gen:Value id="ACTIVITY" value="ISIC4_D"/></gen:ObsKey><gen:ObsValue value="122246.9"/><gen:Attributes><gen:Value id="UNIT_MEASURE" value="PER_1000_USD"/><gen:Value id="TIME_DETAIL" value="2016"/></gen:Attributes></gen:Obs><gen:Obs><gen:ObsKey><gen:Value id="FREQ" value="A"/><gen:Value id="REPORTING_TYPE" value="N"/><gen:Value id="SERIES" value="_L_KG_170301_1A"/><gen:Value id="REF_AREA" value="KG"/><gen:Value id="ACTIVITY" value="ISIC4_D"/></gen:ObsKey><gen:ObsValue value="79828.6"/><gen:Attributes><gen:Value id="UNIT_MEASURE" value="PER_1000_USD"/><gen:Value id="TIME_DETAIL" value="2017"/></gen:Attributes></gen:Obs><gen:Obs><gen:ObsKey><gen:Value id="FREQ" value="A"/><gen:Value id="REPORTING_TYPE" value="N"/><gen:Value id="SERIES" value="_L_KG_170301_1A"/><gen:Value id="REF_AREA" value="KG"/><gen:Value id="ACTIVITY" value="ISIC4_D"/></gen:ObsKey><gen:ObsValue value="15830.6"/><gen:Attributes><gen:Value id="UNIT_MEASURE" value="PER_1000_USD"/><gen:Value id="TIME_DETAIL" value="2018"/></gen:Attributes></gen:Obs><gen:Obs><gen:ObsKey><gen:Value id="FREQ" value="A"/><gen:Value id="REPORTING_TYPE" value="N"/><gen:Value id="SERIES" value="_L_KG_170301_1A"/><gen:Value id="REF_AREA" value="KG"/><gen:Value id="ACTIVITY" value="ISIC4_E"/></gen:ObsKey><gen:ObsValue value="1282.893"/><gen:Attributes><gen:Value id="UNIT_MEASURE" value="PER_1000_USD"/><gen:Value id="TIME_DETAIL" value="2008"/></gen:Attributes></gen:Obs><gen:Obs><gen:ObsKey><gen:Value id="FREQ" value="A"/><gen:Value id="REPORTING_TYPE" value="N"/><gen:Value id="SERIES" value="_L_KG_170301_1A"/><gen:Value id="REF_AREA" value="KG"/><gen:Value id="ACTIVITY" value="ISIC4_E"/></gen:ObsKey><gen:ObsValue value="311.0"/><gen:Attributes><gen:Value id="UNIT_MEASURE" value="PER_1000_USD"/><gen:Value id="TIME_DETAIL" value="2009"/></gen:Attributes></gen:Obs><gen:Obs><gen:ObsKey><gen:Value id="FREQ" value="A"/><gen:Value id="REPORTING_TYPE" value="N"/><gen:Value id="SERIES" value="_L_KG_170301_1A"/><gen:Value id="REF_AREA" value="KG"/><gen:Value id="ACTIVITY" value="ISIC4_E"/></gen:ObsKey><gen:ObsValue value="17.0"/><gen:Attributes><gen:Value id="UNIT_MEASURE" value="PER_1000_USD"/><gen:Value id="TIME_DETAIL" value="2010"/></gen:Attributes></gen:Obs><gen:Obs><gen:ObsKey><gen:Value id="FREQ" value="A"/><gen:Value id="REPORTING_TYPE" value="N"/><gen:Value id="SERIES" value="_L_KG_170301_1A"/><gen:Value id="REF_AREA" value="KG"/><gen:Value id="ACTIVITY" value="ISIC4_E"/></gen:ObsKey><gen:ObsValue value="23.9"/><gen:Attributes><gen:Value id="UNIT_MEASURE" value="PER_1000_USD"/><gen:Value id="TIME_DETAIL" value="2011"/></gen:Attributes></gen:Obs><gen:Obs><gen:ObsKey><gen:Value id="FREQ" value="A"/><gen:Value id="REPORTING_TYPE" value="N"/><gen:Value id="SERIES" value="_L_KG_170301_1A"/><gen:Value id="REF_AREA" value="KG"/><gen:Value id="ACTIVITY" value="ISIC4_E"/></gen:ObsKey><gen:ObsValue value="29.6"/><gen:Attributes><gen:Value id="UNIT_MEASURE" value="PER_1000_USD"/><gen:Value id="TIME_DETAIL" value="2012"/></gen:Attributes></gen:Obs><gen:Obs><gen:ObsKey><gen:Value id="FREQ" value="A"/><gen:Value id="REPORTING_TYPE" value="N"/><gen:Value id="SERIES" value="_L_KG_170301_1A"/><gen:Value id="REF_AREA" value="KG"/><gen:Value id="ACTIVITY" value="ISIC4_E"/></gen:ObsKey><gen:ObsValue value="158.6"/><gen:Attributes><gen:Value id="UNIT_MEASURE" value="PER_1000_USD"/><gen:Value id="TIME_DETAIL" value="2013"/></gen:Attributes></gen:Obs><gen:Obs><gen:ObsKey><gen:Value id="FREQ" value="A"/><gen:Value id="REPORTING_TYPE" value="N"/><gen:Value id="SERIES" value="_L_KG_170301_1A"/><gen:Value id="REF_AREA" value="KG"/><gen:Value id="ACTIVITY" value="ISIC4_E"/></gen:ObsKey><gen:ObsValue value="31.5"/><gen:Attributes><gen:Value id="UNIT_MEASURE" value="PER_1000_USD"/><gen:Value id="TIME_DETAIL" value="2014"/></gen:Attributes></gen:Obs><gen:Obs><gen:ObsKey><gen:Value id="FREQ" value="A"/><gen:Value id="REPORTING_TYPE" value="N"/><gen:Value id="SERIES" value="_L_KG_170301_1A"/><gen:Value id="REF_AREA" value="KG"/><gen:Value id="ACTIVITY" value="ISIC4_E"/></gen:ObsKey><gen:ObsValue value="3.8"/><gen:Attributes><gen:Value id="UNIT_MEASURE" value="PER_1000_USD"/><gen:Value id="TIME_DETAIL" value="2018"/></gen:Attributes></gen:Obs><gen:Obs><gen:ObsKey><gen:Value id="FREQ" value="A"/><gen:Value id="REPORTING_TYPE" value="N"/><gen:Value id="SERIES" value="_L_KG_170301_1A"/><gen:Value id="REF_AREA" value="KG"/><gen:Value id="ACTIVITY" value="ISIC4_F"/></gen:ObsKey><gen:ObsValue value="48949.5"/><gen:Attributes><gen:Value id="UNIT_MEASURE" value="PER_1000_USD"/><gen:Value id="TIME_DETAIL" value="2008"/></gen:Attributes></gen:Obs><gen:Obs><gen:ObsKey><gen:Value id="FREQ" value="A"/><gen:Value id="REPORTING_TYPE" value="N"/><gen:Value id="SERIES" value="_L_KG_170301_1A"/><gen:Value id="REF_AREA" value="KG"/><gen:Value id="ACTIVITY" value="ISIC4_F"/></gen:ObsKey><gen:ObsValue value="21396.9"/><gen:Attributes><gen:Value id="UNIT_MEASURE" value="PER_1000_USD"/><gen:Value id="TIME_DETAIL" value="2009"/></gen:Attributes></gen:Obs><gen:Obs><gen:ObsKey><gen:Value id="FREQ" value="A"/><gen:Value id="REPORTING_TYPE" value="N"/><gen:Value id="SERIES" value="_L_KG_170301_1A"/><gen:Value id="REF_AREA" value="KG"/><gen:Value id="ACTIVITY" value="ISIC4_F"/></gen:ObsKey><gen:ObsValue value="12908.2"/><gen:Attributes><gen:Value id="UNIT_MEASURE" value="PER_1000_USD"/><gen:Value id="TIME_DETAIL" value="2010"/></gen:Attributes></gen:Obs><gen:Obs><gen:ObsKey><gen:Value id="FREQ" value="A"/><gen:Value id="REPORTING_TYPE" value="N"/><gen:Value id="SERIES" value="_L_KG_170301_1A"/><gen:Value id="REF_AREA" value="KG"/><gen:Value id="ACTIVITY" value="ISIC4_F"/></gen:ObsKey><gen:ObsValue value="6404.9"/><gen:Attributes><gen:Value id="UNIT_MEASURE" value="PER_1000_USD"/><gen:Value id="TIME_DETAIL" value="2011"/></gen:Attributes></gen:Obs><gen:Obs><gen:ObsKey><gen:Value id="FREQ" value="A"/><gen:Value id="REPORTING_TYPE" value="N"/><gen:Value id="SERIES" value="_L_KG_170301_1A"/><gen:Value id="REF_AREA" value="KG"/><gen:Value id="ACTIVITY" value="ISIC4_F"/></gen:ObsKey><gen:ObsValue value="27832.6"/><gen:Attributes><gen:Value id="UNIT_MEASURE" value="PER_1000_USD"/><gen:Value id="TIME_DETAIL" value="2012"/></gen:Attributes></gen:Obs><gen:Obs><gen:ObsKey><gen:Value id="FREQ" value="A"/><gen:Value id="REPORTING_TYPE" value="N"/><gen:Value id="SERIES" value="_L_KG_170301_1A"/><gen:Value id="REF_AREA" value="KG"/><gen:Value id="ACTIVITY" value="ISIC4_F"/></gen:ObsKey><gen:ObsValue value="15504.6"/><gen:Attributes><gen:Value id="UNIT_MEASURE" value="PER_1000_USD"/><gen:Value id="TIME_DETAIL" value="2013"/></gen:Attributes></gen:Obs><gen:Obs><gen:ObsKey><gen:Value id="FREQ" value="A"/><gen:Value id="REPORTING_TYPE" value="N"/><gen:Value id="SERIES" value="_L_KG_170301_1A"/><gen:Value id="REF_AREA" value="KG"/><gen:Value id="ACTIVITY" value="ISIC4_F"/></gen:ObsKey><gen:ObsValue value="20045.5"/><gen:Attributes><gen:Value id="UNIT_MEASURE" value="PER_1000_USD"/><gen:Value id="TIME_DETAIL" value="2014"/></gen:Attributes></gen:Obs><gen:Obs><gen:ObsKey><gen:Value id="FREQ" value="A"/><gen:Value id="REPORTING_TYPE" value="N"/><gen:Value id="SERIES" value="_L_KG_170301_1A"/><gen:Value id="REF_AREA" value="KG"/><gen:Value id="ACTIVITY" value="ISIC4_F"/></gen:ObsKey><gen:ObsValue value="107007.6"/><gen:Attributes><gen:Value id="UNIT_MEASURE" value="PER_1000_USD"/><gen:Value id="TIME_DETAIL" value="2015"/></gen:Attributes></gen:Obs><gen:Obs><gen:ObsKey><gen:Value id="FREQ" value="A"/><gen:Value id="REPORTING_TYPE" value="N"/><gen:Value id="SERIES" value="_L_KG_170301_1A"/><gen:Value id="REF_AREA" value="KG"/><gen:Value id="ACTIVITY" value="ISIC4_F"/></gen:ObsKey><gen:ObsValue value="25385.8"/><gen:Attributes><gen:Value id="UNIT_MEASURE" value="PER_1000_USD"/><gen:Value id="TIME_DETAIL" value="2016"/></gen:Attributes></gen:Obs><gen:Obs><gen:ObsKey><gen:Value id="FREQ" value="A"/><gen:Value id="REPORTING_TYPE" value="N"/><gen:Value id="SERIES" value="_L_KG_170301_1A"/><gen:Value id="REF_AREA" value="KG"/><gen:Value id="ACTIVITY" value="ISIC4_F"/></gen:ObsKey><gen:ObsValue value="3070.6"/><gen:Attributes><gen:Value id="UNIT_MEASURE" value="PER_1000_USD"/><gen:Value id="TIME_DETAIL" value="2017"/></gen:Attributes></gen:Obs><gen:Obs><gen:ObsKey><gen:Value id="FREQ" value="A"/><gen:Value id="REPORTING_TYPE" value="N"/><gen:Value id="SERIES" value="_L_KG_170301_1A"/><gen:Value id="REF_AREA" value="KG"/><gen:Value id="ACTIVITY" value="ISIC4_F"/></gen:ObsKey><gen:ObsValue value="71859.5"/><gen:Attributes><gen:Value id="UNIT_MEASURE" value="PER_1000_USD"/><gen:Value id="TIME_DETAIL" value="2018"/></gen:Attributes></gen:Obs><gen:Obs><gen:ObsKey><gen:Value id="FREQ" value="A"/><gen:Value id="REPORTING_TYPE" value="N"/><gen:Value id="SERIES" value="_L_KG_170301_1A"/><gen:Value id="REF_AREA" value="KG"/><gen:Value id="ACTIVITY" value="ISIC4_G"/></gen:ObsKey><gen:ObsValue value="56200.3"/><gen:Attributes><gen:Value id="UNIT_MEASURE" value="PER_1000_USD"/><gen:Value id="TIME_DETAIL" value="2008"/></gen:Attributes></gen:Obs><gen:Obs><gen:ObsKey><gen:Value id="FREQ" value="A"/><gen:Value id="REPORTING_TYPE" value="N"/><gen:Value id="SERIES" value="_L_KG_170301_1A"/><gen:Value id="REF_AREA" value="KG"/><gen:Value id="ACTIVITY" value="ISIC4_G"/></gen:ObsKey><gen:ObsValue value="52960.3"/><gen:Attributes><gen:Value id="UNIT_MEASURE" value="PER_1000_USD"/><gen:Value id="TIME_DETAIL" value="2009"/></gen:Attributes></gen:Obs><gen:Obs><gen:ObsKey><gen:Value id="FREQ" value="A"/><gen:Value id="REPORTING_TYPE" value="N"/><gen:Value id="SERIES" value="_L_KG_170301_1A"/><gen:Value id="REF_AREA" value="KG"/><gen:Value id="ACTIVITY" value="ISIC4_G"/></gen:ObsKey><gen:ObsValue value="53484.3"/><gen:Attributes><gen:Value id="UNIT_MEASURE" value="PER_1000_USD"/><gen:Value id="TIME_DETAIL" value="2010"/></gen:Attributes></gen:Obs><gen:Obs><gen:ObsKey><gen:Value id="FREQ" value="A"/><gen:Value id="REPORTING_TYPE" value="N"/><gen:Value id="SERIES" value="_L_KG_170301_1A"/><gen:Value id="REF_AREA" value="KG"/><gen:Value id="ACTIVITY" value="ISIC4_G"/></gen:ObsKey><gen:ObsValue value="64982.6"/><gen:Attributes><gen:Value id="UNIT_MEASURE" value="PER_1000_USD"/><gen:Value id="TIME_DETAIL" value="2011"/></gen:Attributes></gen:Obs><gen:Obs><gen:ObsKey><gen:Value id="FREQ" value="A"/><gen:Value id="REPORTING_TYPE" value="N"/><gen:Value id="SERIES" value="_L_KG_170301_1A"/><gen:Value id="REF_AREA" value="KG"/><gen:Value id="ACTIVITY" value="ISIC4_G"/></gen:ObsKey><gen:ObsValue value="32625.9"/><gen:Attributes><gen:Value id="UNIT_MEASURE" value="PER_1000_USD"/><gen:Value id="TIME_DETAIL" value="2012"/></gen:Attributes></gen:Obs><gen:Obs><gen:ObsKey><gen:Value id="FREQ" value="A"/><gen:Value id="REPORTING_TYPE" value="N"/><gen:Value id="SERIES" value="_L_KG_170301_1A"/><gen:Value id="REF_AREA" value="KG"/><gen:Value id="ACTIVITY" value="ISIC4_G"/></gen:ObsKey><gen:ObsValue value="66575.3"/><gen:Attributes><gen:Value id="UNIT_MEASURE" value="PER_1000_USD"/><gen:Value id="TIME_DETAIL" value="2013"/></gen:Attributes></gen:Obs><gen:Obs><gen:ObsKey><gen:Value id="FREQ" value="A"/><gen:Value id="REPORTING_TYPE" value="N"/><gen:Value id="SERIES" value="_L_KG_170301_1A"/><gen:Value id="REF_AREA" value="KG"/><gen:Value id="ACTIVITY" value="ISIC4_G"/></gen:ObsKey><gen:ObsValue value="37620.0"/><gen:Attributes><gen:Value id="UNIT_MEASURE" value="PER_1000_USD"/><gen:Value id="TIME_DETAIL" value="2014"/></gen:Attributes></gen:Obs><gen:Obs><gen:ObsKey><gen:Value id="FREQ" value="A"/><gen:Value id="REPORTING_TYPE" value="N"/><gen:Value id="SERIES" value="_L_KG_170301_1A"/><gen:Value id="REF_AREA" value="KG"/><gen:Value id="ACTIVITY" value="ISIC4_G"/></gen:ObsKey><gen:ObsValue value="64832.3"/><gen:Attributes><gen:Value id="UNIT_MEASURE" value="PER_1000_USD"/><gen:Value id="TIME_DETAIL" value="2015"/></gen:Attributes></gen:Obs><gen:Obs><gen:ObsKey><gen:Value id="FREQ" value="A"/><gen:Value id="REPORTING_TYPE" value="N"/><gen:Value id="SERIES" value="_L_KG_170301_1A"/><gen:Value id="REF_AREA" value="KG"/><gen:Value id="ACTIVITY" value="ISIC4_G"/></gen:ObsKey><gen:ObsValue value="13231.0"/><gen:Attributes><gen:Value id="UNIT_MEASURE" value="PER_1000_USD"/><gen:Value id="TIME_DETAIL" value="2016"/></gen:Attributes></gen:Obs><gen:Obs><gen:ObsKey><gen:Value id="FREQ" value="A"/><gen:Value id="REPORTING_TYPE" value="N"/><gen:Value id="SERIES" value="_L_KG_170301_1A"/><gen:Value id="REF_AREA" value="KG"/><gen:Value id="ACTIVITY" value="ISIC4_G"/></gen:ObsKey><gen:ObsValue value="30550.6"/><gen:Attributes><gen:Value id="UNIT_MEASURE" value="PER_1000_USD"/><gen:Value id="TIME_DETAIL" value="2017"/></gen:Attributes></gen:Obs><gen:Obs><gen:ObsKey><gen:Value id="FREQ" value="A"/><gen:Value id="REPORTING_TYPE" value="N"/><gen:Value id="SERIES" value="_L_KG_170301_1A"/><gen:Value id="REF_AREA" value="KG"/><gen:Value id="ACTIVITY" value="ISIC4_G"/></gen:ObsKey><gen:ObsValue value="34533.2"/><gen:Attributes><gen:Value id="UNIT_MEASURE" value="PER_1000_USD"/><gen:Value id="TIME_DETAIL" value="2018"/></gen:Attributes></gen:Obs><gen:Obs><gen:ObsKey><gen:Value id="FREQ" value="A"/><gen:Value id="REPORTING_TYPE" value="N"/><gen:Value id="SERIES" value="_L_KG_170301_1A"/><gen:Value id="REF_AREA" value="KG"/><gen:Value id="ACTIVITY" value="ISIC4_H"/></gen:ObsKey><gen:ObsValue value="15126.3"/><gen:Attributes><gen:Value id="UNIT_MEASURE" value="PER_1000_USD"/><gen:Value id="TIME_DETAIL" value="2008"/></gen:Attributes></gen:Obs><gen:Obs><gen:ObsKey><gen:Value id="FREQ" value="A"/><gen:Value id="REPORTING_TYPE" value="N"/><gen:Value id="SERIES" value="_L_KG_170301_1A"/><gen:Value id="REF_AREA" value="KG"/><gen:Value id="ACTIVITY" value="ISIC4_H"/></gen:ObsKey><gen:ObsValue value="8775.8"/><gen:Attributes><gen:Value id="UNIT_MEASURE" value="PER_1000_USD"/><gen:Value id="TIME_DETAIL" value="2009"/></gen:Attributes></gen:Obs><gen:Obs><gen:ObsKey><gen:Value id="FREQ" value="A"/><gen:Value id="REPORTING_TYPE" value="N"/><gen:Value id="SERIES" value="_L_KG_170301_1A"/><gen:Value id="REF_AREA" value="KG"/><gen:Value id="ACTIVITY" value="ISIC4_H"/></gen:ObsKey><gen:ObsValue value="12167.0"/><gen:Attributes><gen:Value id="UNIT_MEASURE" value="PER_1000_USD"/><gen:Value id="TIME_DETAIL" value="2010"/></gen:Attributes></gen:Obs><gen:Obs><gen:ObsKey><gen:Value id="FREQ" value="A"/><gen:Value id="REPORTING_TYPE" value="N"/><gen:Value id="SERIES" value="_L_KG_170301_1A"/><gen:Value id="REF_AREA" value="KG"/><gen:Value id="ACTIVITY" value="ISIC4_H"/></gen:ObsKey><gen:ObsValue value="36623.8"/><gen:Attributes><gen:Value id="UNIT_MEASURE" value="PER_1000_USD"/><gen:Value id="TIME_DETAIL" value="2011"/></gen:Attributes></gen:Obs><gen:Obs><gen:ObsKey><gen:Value id="FREQ" value="A"/><gen:Value id="REPORTING_TYPE" value="N"/><gen:Value id="SERIES" value="_L_KG_170301_1A"/><gen:Value id="REF_AREA" value="KG"/><gen:Value id="ACTIVITY" value="ISIC4_H"/></gen:ObsKey><gen:ObsValue value="6449.1"/><gen:Attributes><gen:Value id="UNIT_MEASURE" value="PER_1000_USD"/><gen:Value id="TIME_DETAIL" value="2012"/></gen:Attributes></gen:Obs><gen:Obs><gen:ObsKey><gen:Value id="FREQ" value="A"/><gen:Value id="REPORTING_TYPE" value="N"/><gen:Value id="SERIES" value="_L_KG_170301_1A"/><gen:Value id="REF_AREA" value="KG"/><gen:Value id="ACTIVITY" value="ISIC4_H"/></gen:ObsKey><gen:ObsValue value="10062.1"/><gen:Attributes><gen:Value id="UNIT_MEASURE" value="PER_1000_USD"/><gen:Value id="TIME_DETAIL" value="2013"/></gen:Attributes></gen:Obs><gen:Obs><gen:ObsKey><gen:Value id="FREQ" value="A"/><gen:Value id="REPORTING_TYPE" value="N"/><gen:Value id="SERIES" value="_L_KG_170301_1A"/><gen:Value id="REF_AREA" value="KG"/><gen:Value id="ACTIVITY" value="ISIC4_H"/></gen:ObsKey><gen:ObsValue value="6042.6"/><gen:Attributes><gen:Value id="UNIT_MEASURE" value="PER_1000_USD"/><gen:Value id="TIME_DETAIL" value="2014"/></gen:Attributes></gen:Obs><gen:Obs><gen:ObsKey><gen:Value id="FREQ" value="A"/><gen:Value id="REPORTING_TYPE" value="N"/><gen:Value id="SERIES" value="_L_KG_170301_1A"/><gen:Value id="REF_AREA" value="KG"/><gen:Value id="ACTIVITY" value="ISIC4_H"/></gen:ObsKey><gen:ObsValue value="2551.5"/><gen:Attributes><gen:Value id="UNIT_MEASURE" value="PER_1000_USD"/><gen:Value id="TIME_DETAIL" value="2015"/></gen:Attributes></gen:Obs><gen:Obs><gen:ObsKey><gen:Value id="FREQ" value="A"/><gen:Value id="REPORTING_TYPE" value="N"/><gen:Value id="SERIES" value="_L_KG_170301_1A"/><gen:Value id="REF_AREA" value="KG"/><gen:Value id="ACTIVITY" value="ISIC4_H"/></gen:ObsKey><gen:ObsValue value="18.2"/><gen:Attributes><gen:Value id="UNIT_MEASURE" value="PER_1000_USD"/><gen:Value id="TIME_DETAIL" value="2016"/></gen:Attributes></gen:Obs><gen:Obs><gen:ObsKey><gen:Value id="FREQ" value="A"/><gen:Value id="REPORTING_TYPE" value="N"/><gen:Value id="SERIES" value="_L_KG_170301_1A"/><gen:Value id="REF_AREA" value="KG"/><gen:Value id="ACTIVITY" value="ISIC4_H"/></gen:ObsKey><gen:ObsValue value="104.8"/><gen:Attributes><gen:Value id="UNIT_MEASURE" value="PER_1000_USD"/><gen:Value id="TIME_DETAIL" value="2017"/></gen:Attributes></gen:Obs><gen:Obs><gen:ObsKey><gen:Value id="FREQ" value="A"/><gen:Value id="REPORTING_TYPE" value="N"/><gen:Value id="SERIES" value="_L_KG_170301_1A"/><gen:Value id="REF_AREA" value="KG"/><gen:Value id="ACTIVITY" value="ISIC4_H"/></gen:ObsKey><gen:ObsValue value="8726.8"/><gen:Attributes><gen:Value id="UNIT_MEASURE" value="PER_1000_USD"/><gen:Value id="TIME_DETAIL" value="2018"/></gen:Attributes></gen:Obs><gen:Obs><gen:ObsKey><gen:Value id="FREQ" value="A"/><gen:Value id="REPORTING_TYPE" value="N"/><gen:Value id="SERIES" value="_L_KG_170301_1A"/><gen:Value id="REF_AREA" value="KG"/><gen:Value id="ACTIVITY" value="ISIC4_I"/></gen:ObsKey><gen:ObsValue value="2386.663"/><gen:Attributes><gen:Value id="UNIT_MEASURE" value="PER_1000_USD"/><gen:Value id="TIME_DETAIL" value="2008"/></gen:Attributes></gen:Obs><gen:Obs><gen:ObsKey><gen:Value id="FREQ" value="A"/><gen:Value id="REPORTING_TYPE" value="N"/><gen:Value id="SERIES" value="_L_KG_170301_1A"/><gen:Value id="REF_AREA" value="KG"/><gen:Value id="ACTIVITY" value="ISIC4_I"/></gen:ObsKey><gen:ObsValue value="4782.8"/><gen:Attributes><gen:Value id="UNIT_MEASURE" value="PER_1000_USD"/><gen:Value id="TIME_DETAIL" value="2009"/></gen:Attributes></gen:Obs><gen:Obs><gen:ObsKey><gen:Value id="FREQ" value="A"/><gen:Value id="REPORTING_TYPE" value="N"/><gen:Value id="SERIES" value="_L_KG_170301_1A"/><gen:Value id="REF_AREA" value="KG"/><gen:Value id="ACTIVITY" value="ISIC4_I"/></gen:ObsKey><gen:ObsValue value="8158.1"/><gen:Attributes><gen:Value id="UNIT_MEASURE" value="PER_1000_USD"/><gen:Value id="TIME_DETAIL" value="2010"/></gen:Attributes></gen:Obs><gen:Obs><gen:ObsKey><gen:Value id="FREQ" value="A"/><gen:Value id="REPORTING_TYPE" value="N"/><gen:Value id="SERIES" value="_L_KG_170301_1A"/><gen:Value id="REF_AREA" value="KG"/><gen:Value id="ACTIVITY" value="ISIC4_I"/></gen:ObsKey><gen:ObsValue value="4010.7"/><gen:Attributes><gen:Value id="UNIT_MEASURE" value="PER_1000_USD"/><gen:Value id="TIME_DETAIL" value="2011"/></gen:Attributes></gen:Obs><gen:Obs><gen:ObsKey><gen:Value id="FREQ" value="A"/><gen:Value id="REPORTING_TYPE" value="N"/><gen:Value id="SERIES" value="_L_KG_170301_1A"/><gen:Value id="REF_AREA" value="KG"/><gen:Value id="ACTIVITY" value="ISIC4_I"/></gen:ObsKey><gen:ObsValue value="1759.8"/><gen:Attributes><gen:Value id="UNIT_MEASURE" value="PER_1000_USD"/><gen:Value id="TIME_DETAIL" value="2012"/></gen:Attributes></gen:Obs><gen:Obs><gen:ObsKey><gen:Value id="FREQ" value="A"/><gen:Value id="REPORTING_TYPE" value="N"/><gen:Value id="SERIES" value="_L_KG_170301_1A"/><gen:Value id="REF_AREA" value="KG"/><gen:Value id="ACTIVITY" value="ISIC4_I"/></gen:ObsKey><gen:ObsValue value="473.6"/><gen:Attributes><gen:Value id="UNIT_MEASURE" value="PER_1000_USD"/><gen:Value id="TIME_DETAIL" value="2013"/></gen:Attributes></gen:Obs><gen:Obs><gen:ObsKey><gen:Value id="FREQ" value="A"/><gen:Value id="REPORTING_TYPE" value="N"/><gen:Value id="SERIES" value="_L_KG_170301_1A"/><gen:Value id="REF_AREA" value="KG"/><gen:Value id="ACTIVITY" value="ISIC4_I"/></gen:ObsKey><gen:ObsValue value="219.3"/><gen:Attributes><gen:Value id="UNIT_MEASURE" value="PER_1000_USD"/><gen:Value id="TIME_DETAIL" value="2014"/></gen:Attributes></gen:Obs><gen:Obs><gen:ObsKey><gen:Value id="FREQ" value="A"/><gen:Value id="REPORTING_TYPE" value="N"/><gen:Value id="SERIES" value="_L_KG_170301_1A"/><gen:Value id="REF_AREA" value="KG"/><gen:Value id="ACTIVITY" value="ISIC4_I"/></gen:ObsKey><gen:ObsValue value="38.4"/><gen:Attributes><gen:Value id="UNIT_MEASURE" value="PER_1000_USD"/><gen:Value id="TIME_DETAIL" value="2015"/></gen:Attributes></gen:Obs><gen:Obs><gen:ObsKey><gen:Value id="FREQ" value="A"/><gen:Value id="REPORTING_TYPE" value="N"/><gen:Value id="SERIES" value="_L_KG_170301_1A"/><gen:Value id="REF_AREA" value="KG"/><gen:Value id="ACTIVITY" value="ISIC4_I"/></gen:ObsKey><gen:ObsValue value="2102.5"/><gen:Attributes><gen:Value id="UNIT_MEASURE" value="PER_1000_USD"/><gen:Value id="TIME_DETAIL" value="2016"/></gen:Attributes></gen:Obs><gen:Obs><gen:ObsKey><gen:Value id="FREQ" value="A"/><gen:Value id="REPORTING_TYPE" value="N"/><gen:Value id="SERIES" value="_L_KG_170301_1A"/><gen:Value id="REF_AREA" value="KG"/><gen:Value id="ACTIVITY" value="ISIC4_I"/></gen:ObsKey><gen:ObsValue value="2624.7"/><gen:Attributes><gen:Value id="UNIT_MEASURE" value="PER_1000_USD"/><gen:Value id="TIME_DETAIL" value="2017"/></gen:Attributes></gen:Obs><gen:Obs><gen:ObsKey><gen:Value id="FREQ" value="A"/><gen:Value id="REPORTING_TYPE" value="N"/><gen:Value id="SERIES" value="_L_KG_170301_1A"/><gen:Value id="REF_AREA" value="KG"/><gen:Value id="ACTIVITY" value="ISIC4_I"/></gen:ObsKey><gen:ObsValue value="638.2"/><gen:Attributes><gen:Value id="UNIT_MEASURE" value="PER_1000_USD"/><gen:Value id="TIME_DETAIL" value="2018"/></gen:Attributes></gen:Obs><gen:Obs><gen:ObsKey><gen:Value id="FREQ" value="A"/><gen:Value id="REPORTING_TYPE" value="N"/><gen:Value id="SERIES" value="_L_KG_170301_1A"/><gen:Value id="REF_AREA" value="KG"/><gen:Value id="ACTIVITY" value="ISIC4_J"/></gen:ObsKey><gen:ObsValue value="2449.8"/><gen:Attributes><gen:Value id="UNIT_MEASURE" value="PER_1000_USD"/><gen:Value id="TIME_DETAIL" value="2008"/></gen:Attributes></gen:Obs><gen:Obs><gen:ObsKey><gen:Value id="FREQ" value="A"/><gen:Value id="REPORTING_TYPE" value="N"/><gen:Value id="SERIES" value="_L_KG_170301_1A"/><gen:Value id="REF_AREA" value="KG"/><gen:Value id="ACTIVITY" value="ISIC4_J"/></gen:ObsKey><gen:ObsValue value="13580.1"/><gen:Attributes><gen:Value id="UNIT_MEASURE" value="PER_1000_USD"/><gen:Value id="TIME_DETAIL" value="2009"/></gen:Attributes></gen:Obs><gen:Obs><gen:ObsKey><gen:Value id="FREQ" value="A"/><gen:Value id="REPORTING_TYPE" value="N"/><gen:Value id="SERIES" value="_L_KG_170301_1A"/><gen:Value id="REF_AREA" value="KG"/><gen:Value id="ACTIVITY" value="ISIC4_J"/></gen:ObsKey><gen:ObsValue value="922.5"/><gen:Attributes><gen:Value id="UNIT_MEASURE" value="PER_1000_USD"/><gen:Value id="TIME_DETAIL" value="2010"/></gen:Attributes></gen:Obs><gen:Obs><gen:ObsKey><gen:Value id="FREQ" value="A"/><gen:Value id="REPORTING_TYPE" value="N"/><gen:Value id="SERIES" value="_L_KG_170301_1A"/><gen:Value id="REF_AREA" value="KG"/><gen:Value id="ACTIVITY" value="ISIC4_J"/></gen:ObsKey><gen:ObsValue value="3243.4"/><gen:Attributes><gen:Value id="UNIT_MEASURE" value="PER_1000_USD"/><gen:Value id="TIME_DETAIL" value="2011"/></gen:Attributes></gen:Obs><gen:Obs><gen:ObsKey><gen:Value id="FREQ" value="A"/><gen:Value id="REPORTING_TYPE" value="N"/><gen:Value id="SERIES" value="_L_KG_170301_1A"/><gen:Value id="REF_AREA" value="KG"/><gen:Value id="ACTIVITY" value="ISIC4_J"/></gen:ObsKey><gen:ObsValue value="2642.0"/><gen:Attributes><gen:Value id="UNIT_MEASURE" value="PER_1000_USD"/><gen:Value id="TIME_DETAIL" value="2012"/></gen:Attributes></gen:Obs><gen:Obs><gen:ObsKey><gen:Value id="FREQ" value="A"/><gen:Value id="REPORTING_TYPE" value="N"/><gen:Value id="SERIES" value="_L_KG_170301_1A"/><gen:Value id="REF_AREA" value="KG"/><gen:Value id="ACTIVITY" value="ISIC4_J"/></gen:ObsKey><gen:ObsValue value="3235.3"/><gen:Attributes><gen:Value id="UNIT_MEASURE" value="PER_1000_USD"/><gen:Value id="TIME_DETAIL" value="2013"/></gen:Attributes></gen:Obs><gen:Obs><gen:ObsKey><gen:Value id="FREQ" value="A"/><gen:Value id="REPORTING_TYPE" value="N"/><gen:Value id="SERIES" value="_L_KG_170301_1A"/><gen:Value id="REF_AREA" value="KG"/><gen:Value id="ACTIVITY" value="ISIC4_J"/></gen:ObsKey><gen:ObsValue value="13168.7"/><gen:Attributes><gen:Value id="UNIT_MEASURE" value="PER_1000_USD"/><gen:Value id="TIME_DETAIL" value="2014"/></gen:Attributes></gen:Obs><gen:Obs><gen:ObsKey><gen:Value id="FREQ" value="A"/><gen:Value id="REPORTING_TYPE" value="N"/><gen:Value id="SERIES" value="_L_KG_170301_1A"/><gen:Value id="REF_AREA" value="KG"/><gen:Value id="ACTIVITY" value="ISIC4_J"/></gen:ObsKey><gen:ObsValue value="5699.3"/><gen:Attributes><gen:Value id="UNIT_MEASURE" value="PER_1000_USD"/><gen:Value id="TIME_DETAIL" value="2015"/></gen:Attributes></gen:Obs><gen:Obs><gen:ObsKey><gen:Value id="FREQ" value="A"/><gen:Value id="REPORTING_TYPE" value="N"/><gen:Value id="SERIES" value="_L_KG_170301_1A"/><gen:Value id="REF_AREA" value="KG"/><gen:Value id="ACTIVITY" value="ISIC4_J"/></gen:ObsKey><gen:ObsValue value="1251.0"/><gen:Attributes><gen:Value id="UNIT_MEASURE" value="PER_1000_USD"/><gen:Value id="TIME_DETAIL" value="2016"/></gen:Attributes></gen:Obs><gen:Obs><gen:ObsKey><gen:Value id="FREQ" value="A"/><gen:Value id="REPORTING_TYPE" value="N"/><gen:Value id="SERIES" value="_L_KG_170301_1A"/><gen:Value id="REF_AREA" value="KG"/><gen:Value id="ACTIVITY" value="ISIC4_J"/></gen:ObsKey><gen:ObsValue value="14422.4"/><gen:Attributes><gen:Value id="UNIT_MEASURE" value="PER_1000_USD"/><gen:Value id="TIME_DETAIL" value="2017"/></gen:Attributes></gen:Obs><gen:Obs><gen:ObsKey><gen:Value id="FREQ" value="A"/><gen:Value id="REPORTING_TYPE" value="N"/><gen:Value id="SERIES" value="_L_KG_170301_1A"/><gen:Value id="REF_AREA" value="KG"/><gen:Value id="ACTIVITY" value="ISIC4_J"/></gen:ObsKey><gen:ObsValue value="52603.8"/><gen:Attributes><gen:Value id="UNIT_MEASURE" value="PER_1000_USD"/><gen:Value id="TIME_DETAIL" value="2018"/></gen:Attributes></gen:Obs><gen:Obs><gen:ObsKey><gen:Value id="FREQ" value="A"/><gen:Value id="REPORTING_TYPE" value="N"/><gen:Value id="SERIES" value="_L_KG_170301_1A"/><gen:Value id="REF_AREA" value="KG"/><gen:Value id="ACTIVITY" value="ISIC4_K"/></gen:ObsKey><gen:ObsValue value="347140.38899999997"/><gen:Attributes><gen:Value id="UNIT_MEASURE" value="PER_1000_USD"/><gen:Value id="TIME_DETAIL" value="2008"/></gen:Attributes></gen:Obs><gen:Obs><gen:ObsKey><gen:Value id="FREQ" value="A"/><gen:Value id="REPORTING_TYPE" value="N"/><gen:Value id="SERIES" value="_L_KG_170301_1A"/><gen:Value id="REF_AREA" value="KG"/><gen:Value id="ACTIVITY" value="ISIC4_K"/></gen:ObsKey><gen:ObsValue value="250155.9"/><gen:Attributes><gen:Value id="UNIT_MEASURE" value="PER_1000_USD"/><gen:Value id="TIME_DETAIL" value="2009"/></gen:Attributes></gen:Obs><gen:Obs><gen:ObsKey><gen:Value id="FREQ" value="A"/><gen:Value id="REPORTING_TYPE" value="N"/><gen:Value id="SERIES" value="_L_KG_170301_1A"/><gen:Value id="REF_AREA" value="KG"/><gen:Value id="ACTIVITY" value="ISIC4_K"/></gen:ObsKey><gen:ObsValue value="34882.2"/><gen:Attributes><gen:Value id="UNIT_MEASURE" value="PER_1000_USD"/><gen:Value id="TIME_DETAIL" value="2010"/></gen:Attributes></gen:Obs><gen:Obs><gen:ObsKey><gen:Value id="FREQ" value="A"/><gen:Value id="REPORTING_TYPE" value="N"/><gen:Value id="SERIES" value="_L_KG_170301_1A"/><gen:Value id="REF_AREA" value="KG"/><gen:Value id="ACTIVITY" value="ISIC4_K"/></gen:ObsKey><gen:ObsValue value="48145.0"/><gen:Attributes><gen:Value id="UNIT_MEASURE" value="PER_1000_USD"/><gen:Value id="TIME_DETAIL" value="2011"/></gen:Attributes></gen:Obs><gen:Obs><gen:ObsKey><gen:Value id="FREQ" value="A"/><gen:Value id="REPORTING_TYPE" value="N"/><gen:Value id="SERIES" value="_L_KG_170301_1A"/><gen:Value id="REF_AREA" value="KG"/><gen:Value id="ACTIVITY" value="ISIC4_K"/></gen:ObsKey><gen:ObsValue value="42233.9"/><gen:Attributes><gen:Value id="UNIT_MEASURE" value="PER_1000_USD"/><gen:Value id="TIME_DETAIL" value="2012"/></gen:Attributes></gen:Obs><gen:Obs><gen:ObsKey><gen:Value id="FREQ" value="A"/><gen:Value id="REPORTING_TYPE" value="N"/><gen:Value id="SERIES" value="_L_KG_170301_1A"/><gen:Value id="REF_AREA" value="KG"/><gen:Value id="ACTIVITY" value="ISIC4_K"/></gen:ObsKey><gen:ObsValue value="99847.3"/><gen:Attributes><gen:Value id="UNIT_MEASURE" value="PER_1000_USD"/><gen:Value id="TIME_DETAIL" value="2013"/></gen:Attributes></gen:Obs><gen:Obs><gen:ObsKey><gen:Value id="FREQ" value="A"/><gen:Value id="REPORTING_TYPE" value="N"/><gen:Value id="SERIES" value="_L_KG_170301_1A"/><gen:Value id="REF_AREA" value="KG"/><gen:Value id="ACTIVITY" value="ISIC4_K"/></gen:ObsKey><gen:ObsValue value="28495.0"/><gen:Attributes><gen:Value id="UNIT_MEASURE" value="PER_1000_USD"/><gen:Value id="TIME_DETAIL" value="2014"/></gen:Attributes></gen:Obs><gen:Obs><gen:ObsKey><gen:Value id="FREQ" value="A"/><gen:Value id="REPORTING_TYPE" value="N"/><gen:Value id="SERIES" value="_L_KG_170301_1A"/><gen:Value id="REF_AREA" value="KG"/><gen:Value id="ACTIVITY" value="ISIC4_K"/></gen:ObsKey><gen:ObsValue value="411883.8"/><gen:Attributes><gen:Value id="UNIT_MEASURE" value="PER_1000_USD"/><gen:Value id="TIME_DETAIL" value="2015"/></gen:Attributes></gen:Obs><gen:Obs><gen:ObsKey><gen:Value id="FREQ" value="A"/><gen:Value id="REPORTING_TYPE" value="N"/><gen:Value id="SERIES" value="_L_KG_170301_1A"/><gen:Value id="REF_AREA" value="KG"/><gen:Value id="ACTIVITY" value="ISIC4_K"/></gen:ObsKey><gen:ObsValue value="178724.5"/><gen:Attributes><gen:Value id="UNIT_MEASURE" value="PER_1000_USD"/><gen:Value id="TIME_DETAIL" value="2016"/></gen:Attributes></gen:Obs><gen:Obs><gen:ObsKey><gen:Value id="FREQ" value="A"/><gen:Value id="REPORTING_TYPE" value="N"/><gen:Value id="SERIES" value="_L_KG_170301_1A"/><gen:Value id="REF_AREA" value="KG"/><gen:Value id="ACTIVITY" value="ISIC4_K"/></gen:ObsKey><gen:ObsValue value="81475.8"/><gen:Attributes><gen:Value id="UNIT_MEASURE" value="PER_1000_USD"/><gen:Value id="TIME_DETAIL" value="2017"/></gen:Attributes></gen:Obs><gen:Obs><gen:ObsKey><gen:Value id="FREQ" value="A"/><gen:Value id="REPORTING_TYPE" value="N"/><gen:Value id="SERIES" value="_L_KG_170301_1A"/><gen:Value id="REF_AREA" value="KG"/><gen:Value id="ACTIVITY" value="ISIC4_K"/></gen:ObsKey><gen:ObsValue value="53939.5"/><gen:Attributes><gen:Value id="UNIT_MEASURE" value="PER_1000_USD"/><gen:Value id="TIME_DETAIL" value="2018"/></gen:Attributes></gen:Obs><gen:Obs><gen:ObsKey><gen:Value id="FREQ" value="A"/><gen:Value id="REPORTING_TYPE" value="N"/><gen:Value id="SERIES" value="_L_KG_170301_1A"/><gen:Value id="REF_AREA" value="KG"/><gen:Value id="ACTIVITY" value="ISIC4_L"/></gen:ObsKey><gen:ObsValue value="314.1"/><gen:Attributes><gen:Value id="UNIT_MEASURE" value="PER_1000_USD"/><gen:Value id="TIME_DETAIL" value="2010"/></gen:Attributes></gen:Obs><gen:Obs><gen:ObsKey><gen:Value id="FREQ" value="A"/><gen:Value id="REPORTING_TYPE" value="N"/><gen:Value id="SERIES" value="_L_KG_170301_1A"/><gen:Value id="REF_AREA" value="KG"/><gen:Value id="ACTIVITY" value="ISIC4_L"/></gen:ObsKey><gen:ObsValue value="241.2"/><gen:Attributes><gen:Value id="UNIT_MEASURE" value="PER_1000_USD"/><gen:Value id="TIME_DETAIL" value="2011"/></gen:Attributes></gen:Obs><gen:Obs><gen:ObsKey><gen:Value id="FREQ" value="A"/><gen:Value id="REPORTING_TYPE" value="N"/><gen:Value id="SERIES" value="_L_KG_170301_1A"/><gen:Value id="REF_AREA" value="KG"/><gen:Value id="ACTIVITY" value="ISIC4_L"/></gen:ObsKey><gen:ObsValue value="3961.3"/><gen:Attributes><gen:Value id="UNIT_MEASURE" value="PER_1000_USD"/><gen:Value id="TIME_DETAIL" value="2012"/></gen:Attributes></gen:Obs><gen:Obs><gen:ObsKey><gen:Value id="FREQ" value="A"/><gen:Value id="REPORTING_TYPE" value="N"/><gen:Value id="SERIES" value="_L_KG_170301_1A"/><gen:Value id="REF_AREA" value="KG"/><gen:Value id="ACTIVITY" value="ISIC4_L"/></gen:ObsKey><gen:ObsValue value="2567.9"/><gen:Attributes><gen:Value id="UNIT_MEASURE" value="PER_1000_USD"/><gen:Value id="TIME_DETAIL" value="2013"/></gen:Attributes></gen:Obs><gen:Obs><gen:ObsKey><gen:Value id="FREQ" value="A"/><gen:Value id="REPORTING_TYPE" value="N"/><gen:Value id="SERIES" value="_L_KG_170301_1A"/><gen:Value id="REF_AREA" value="KG"/><gen:Value id="ACTIVITY" value="ISIC4_L"/></gen:ObsKey><gen:ObsValue value="3071.3"/><gen:Attributes><gen:Value id="UNIT_MEASURE" value="PER_1000_USD"/><gen:Value id="TIME_DETAIL" value="2014"/></gen:Attributes></gen:Obs><gen:Obs><gen:ObsKey><gen:Value id="FREQ" value="A"/><gen:Value id="REPORTING_TYPE" value="N"/><gen:Value id="SERIES" value="_L_KG_170301_1A"/><gen:Value id="REF_AREA" value="KG"/><gen:Value id="ACTIVITY" value="ISIC4_L"/></gen:ObsKey><gen:ObsValue value="2845.7"/><gen:Attributes><gen:Value id="UNIT_MEASURE" value="PER_1000_USD"/><gen:Value id="TIME_DETAIL" value="2015"/></gen:Attributes></gen:Obs><gen:Obs><gen:ObsKey><gen:Value id="FREQ" value="A"/><gen:Value id="REPORTING_TYPE" value="N"/><gen:Value id="SERIES" value="_L_KG_170301_1A"/><gen:Value id="REF_AREA" value="KG"/><gen:Value id="ACTIVITY" value="ISIC4_L"/></gen:ObsKey><gen:ObsValue value="216.8"/><gen:Attributes><gen:Value id="UNIT_MEASURE" value="PER_1000_USD"/><gen:Value id="TIME_DETAIL" value="2016"/></gen:Attributes></gen:Obs><gen:Obs><gen:ObsKey><gen:Value id="FREQ" value="A"/><gen:Value id="REPORTING_TYPE" value="N"/><gen:Value id="SERIES" value="_L_KG_170301_1A"/><gen:Value id="REF_AREA" value="KG"/><gen:Value id="ACTIVITY" value="ISIC4_L"/></gen:ObsKey><gen:ObsValue value="1.1"/><gen:Attributes><gen:Value id="UNIT_MEASURE" value="PER_1000_USD"/><gen:Value id="TIME_DETAIL" value="2017"/></gen:Attributes></gen:Obs><gen:Obs><gen:ObsKey><gen:Value id="FREQ" value="A"/><gen:Value id="REPORTING_TYPE" value="N"/><gen:Value id="SERIES" value="_L_KG_170301_1A"/><gen:Value id="REF_AREA" value="KG"/><gen:Value id="ACTIVITY" value="ISIC4_L"/></gen:ObsKey><gen:ObsValue value="729.6"/><gen:Attributes><gen:Value id="UNIT_MEASURE" value="PER_1000_USD"/><gen:Value id="TIME_DETAIL" value="2018"/></gen:Attributes></gen:Obs><gen:Obs><gen:ObsKey><gen:Value id="FREQ" value="A"/><gen:Value id="REPORTING_TYPE" value="N"/><gen:Value id="SERIES" value="_L_KG_170301_1A"/><gen:Value id="REF_AREA" value="KG"/><gen:Value id="ACTIVITY" value="ISIC4_M"/></gen:ObsKey><gen:ObsValue value="146708.1692"/><gen:Attributes><gen:Value id="UNIT_MEASURE" value="PER_1000_USD"/><gen:Value id="TIME_DETAIL" value="2008"/></gen:Attributes></gen:Obs><gen:Obs><gen:ObsKey><gen:Value id="FREQ" value="A"/><gen:Value id="REPORTING_TYPE" value="N"/><gen:Value id="SERIES" value="_L_KG_170301_1A"/><gen:Value id="REF_AREA" value="KG"/><gen:Value id="ACTIVITY" value="ISIC4_M"/></gen:ObsKey><gen:ObsValue value="148003.4"/><gen:Attributes><gen:Value id="UNIT_MEASURE" value="PER_1000_USD"/><gen:Value id="TIME_DETAIL" value="2009"/></gen:Attributes></gen:Obs><gen:Obs><gen:ObsKey><gen:Value id="FREQ" value="A"/><gen:Value id="REPORTING_TYPE" value="N"/><gen:Value id="SERIES" value="_L_KG_170301_1A"/><gen:Value id="REF_AREA" value="KG"/><gen:Value id="ACTIVITY" value="ISIC4_M"/></gen:ObsKey><gen:ObsValue value="210779.0"/><gen:Attributes><gen:Value id="UNIT_MEASURE" value="PER_1000_USD"/><gen:Value id="TIME_DETAIL" value="2010"/></gen:Attributes></gen:Obs><gen:Obs><gen:ObsKey><gen:Value id="FREQ" value="A"/><gen:Value id="REPORTING_TYPE" value="N"/><gen:Value id="SERIES" value="_L_KG_170301_1A"/><gen:Value id="REF_AREA" value="KG"/><gen:Value id="ACTIVITY" value="ISIC4_M"/></gen:ObsKey><gen:ObsValue value="169475.1"/><gen:Attributes><gen:Value id="UNIT_MEASURE" value="PER_1000_USD"/><gen:Value id="TIME_DETAIL" value="2011"/></gen:Attributes></gen:Obs><gen:Obs><gen:ObsKey><gen:Value id="FREQ" value="A"/><gen:Value id="REPORTING_TYPE" value="N"/><gen:Value id="SERIES" value="_L_KG_170301_1A"/><gen:Value id="REF_AREA" value="KG"/><gen:Value id="ACTIVITY" value="ISIC4_M"/></gen:ObsKey><gen:ObsValue value="186849.8"/><gen:Attributes><gen:Value id="UNIT_MEASURE" value="PER_1000_USD"/><gen:Value id="TIME_DETAIL" value="2012"/></gen:Attributes></gen:Obs><gen:Obs><gen:ObsKey><gen:Value id="FREQ" value="A"/><gen:Value id="REPORTING_TYPE" value="N"/><gen:Value id="SERIES" value="_L_KG_170301_1A"/><gen:Value id="REF_AREA" value="KG"/><gen:Value id="ACTIVITY" value="ISIC4_M"/></gen:ObsKey><gen:ObsValue value="403375.4"/><gen:Attributes><gen:Value id="UNIT_MEASURE" value="PER_1000_USD"/><gen:Value id="TIME_DETAIL" value="2013"/></gen:Attributes></gen:Obs><gen:Obs><gen:ObsKey><gen:Value id="FREQ" value="A"/><gen:Value id="REPORTING_TYPE" value="N"/><gen:Value id="SERIES" value="_L_KG_170301_1A"/><gen:Value id="REF_AREA" value="KG"/><gen:Value id="ACTIVITY" value="ISIC4_M"/></gen:ObsKey><gen:ObsValue value="228570.3"/><gen:Attributes><gen:Value id="UNIT_MEASURE" value="PER_1000_USD"/><gen:Value id="TIME_DETAIL" value="2014"/></gen:Attributes></gen:Obs><gen:Obs><gen:ObsKey><gen:Value id="FREQ" value="A"/><gen:Value id="REPORTING_TYPE" value="N"/><gen:Value id="SERIES" value="_L_KG_170301_1A"/><gen:Value id="REF_AREA" value="KG"/><gen:Value id="ACTIVITY" value="ISIC4_M"/></gen:ObsKey><gen:ObsValue value="261903.2"/><gen:Attributes><gen:Value id="UNIT_MEASURE" value="PER_1000_USD"/><gen:Value id="TIME_DETAIL" value="2015"/></gen:Attributes></gen:Obs><gen:Obs><gen:ObsKey><gen:Value id="FREQ" value="A"/><gen:Value id="REPORTING_TYPE" value="N"/><gen:Value id="SERIES" value="_L_KG_170301_1A"/><gen:Value id="REF_AREA" value="KG"/><gen:Value id="ACTIVITY" value="ISIC4_M"/></gen:ObsKey><gen:ObsValue value="164965.9"/><gen:Attributes><gen:Value id="UNIT_MEASURE" value="PER_1000_USD"/><gen:Value id="TIME_DETAIL" value="2016"/></gen:Attributes></gen:Obs><gen:Obs><gen:ObsKey><gen:Value id="FREQ" value="A"/><gen:Value id="REPORTING_TYPE" value="N"/><gen:Value id="SERIES" value="_L_KG_170301_1A"/><gen:Value id="REF_AREA" value="KG"/><gen:Value id="ACTIVITY" value="ISIC4_M"/></gen:ObsKey><gen:ObsValue value="132449.4"/><gen:Attributes><gen:Value id="UNIT_MEASURE" value="PER_1000_USD"/><gen:Value id="TIME_DETAIL" value="2017"/></gen:Attributes></gen:Obs><gen:Obs><gen:ObsKey><gen:Value id="FREQ" value="A"/><gen:Value id="REPORTING_TYPE" value="N"/><gen:Value id="SERIES" value="_L_KG_170301_1A"/><gen:Value id="REF_AREA" value="KG"/><gen:Value id="ACTIVITY" value="ISIC4_M"/></gen:ObsKey><gen:ObsValue value="142129.0"/><gen:Attributes><gen:Value id="UNIT_MEASURE" value="PER_1000_USD"/><gen:Value id="TIME_DETAIL" value="2018"/></gen:Attributes></gen:Obs><gen:Obs><gen:ObsKey><gen:Value id="FREQ" value="A"/><gen:Value id="REPORTING_TYPE" value="N"/><gen:Value id="SERIES" value="_L_KG_170301_1A"/><gen:Value id="REF_AREA" value="KG"/><gen:Value id="ACTIVITY" value="ISIC4_N"/></gen:ObsKey><gen:ObsValue value="0.2841"/><gen:Attributes><gen:Value id="UNIT_MEASURE" value="PER_1000_USD"/><gen:Value id="TIME_DETAIL" value="2008"/></gen:Attributes></gen:Obs><gen:Obs><gen:ObsKey><gen:Value id="FREQ" value="A"/><gen:Value id="REPORTING_TYPE" value="N"/><gen:Value id="SERIES" value="_L_KG_170301_1A"/><gen:Value id="REF_AREA" value="KG"/><gen:Value id="ACTIVITY" value="ISIC4_N"/></gen:ObsKey><gen:ObsValue value="9.3"/><gen:Attributes><gen:Value id="UNIT_MEASURE" value="PER_1000_USD"/><gen:Value id="TIME_DETAIL" value="2009"/></gen:Attributes></gen:Obs><gen:Obs><gen:ObsKey><gen:Value id="FREQ" value="A"/><gen:Value id="REPORTING_TYPE" value="N"/><gen:Value id="SERIES" value="_L_KG_170301_1A"/><gen:Value id="REF_AREA" value="KG"/><gen:Value id="ACTIVITY" value="ISIC4_N"/></gen:ObsKey><gen:ObsValue value="2.4"/><gen:Attributes><gen:Value id="UNIT_MEASURE" value="PER_1000_USD"/><gen:Value id="TIME_DETAIL" value="2010"/></gen:Attributes></gen:Obs><gen:Obs><gen:ObsKey><gen:Value id="FREQ" value="A"/><gen:Value id="REPORTING_TYPE" value="N"/><gen:Value id="SERIES" value="_L_KG_170301_1A"/><gen:Value id="REF_AREA" value="KG"/><gen:Value id="ACTIVITY" value="ISIC4_N"/></gen:ObsKey><gen:ObsValue value="1.7"/><gen:Attributes><gen:Value id="UNIT_MEASURE" value="PER_1000_USD"/><gen:Value id="TIME_DETAIL" value="2011"/></gen:Attributes></gen:Obs><gen:Obs><gen:ObsKey><gen:Value id="FREQ" value="A"/><gen:Value id="REPORTING_TYPE" value="N"/><gen:Value id="SERIES" value="_L_KG_170301_1A"/><gen:Value id="REF_AREA" value="KG"/><gen:Value id="ACTIVITY" value="ISIC4_N"/></gen:ObsKey><gen:ObsValue value="1083.0"/><gen:Attributes><gen:Value id="UNIT_MEASURE" value="PER_1000_USD"/><gen:Value id="TIME_DETAIL" value="2012"/></gen:Attributes></gen:Obs><gen:Obs><gen:ObsKey><gen:Value id="FREQ" value="A"/><gen:Value id="REPORTING_TYPE" value="N"/><gen:Value id="SERIES" value="_L_KG_170301_1A"/><gen:Value id="REF_AREA" value="KG"/><gen:Value id="ACTIVITY" value="ISIC4_N"/></gen:ObsKey><gen:ObsValue value="17.1"/><gen:Attributes><gen:Value id="UNIT_MEASURE" value="PER_1000_USD"/><gen:Value id="TIME_DETAIL" value="2013"/></gen:Attributes></gen:Obs><gen:Obs><gen:ObsKey><gen:Value id="FREQ" value="A"/><gen:Value id="REPORTING_TYPE" value="N"/><gen:Value id="SERIES" value="_L_KG_170301_1A"/><gen:Value id="REF_AREA" value="KG"/><gen:Value id="ACTIVITY" value="ISIC4_N"/></gen:ObsKey><gen:ObsValue value="11.1"/><gen:Attributes><gen:Value id="UNIT_MEASURE" value="PER_1000_USD"/><gen:Value id="TIME_DETAIL" value="2014"/></gen:Attributes></gen:Obs><gen:Obs><gen:ObsKey><gen:Value id="FREQ" value="A"/><gen:Value id="REPORTING_TYPE" value="N"/><gen:Value id="SERIES" value="_L_KG_170301_1A"/><gen:Value id="REF_AREA" value="KG"/><gen:Value id="ACTIVITY" value="ISIC4_N"/></gen:ObsKey><gen:ObsValue value="0.8"/><gen:Attributes><gen:Value id="UNIT_MEASURE" value="PER_1000_USD"/><gen:Value id="TIME_DETAIL" value="2015"/></gen:Attributes></gen:Obs><gen:Obs><gen:ObsKey><gen:Value id="FREQ" value="A"/><gen:Value id="REPORTING_TYPE" value="N"/><gen:Value id="SERIES" value="_L_KG_170301_1A"/><gen:Value id="REF_AREA" value="KG"/><gen:Value id="ACTIVITY" value="ISIC4_N"/></gen:ObsKey><gen:ObsValue value="65.4"/><gen:Attributes><gen:Value id="UNIT_MEASURE" value="PER_1000_USD"/><gen:Value id="TIME_DETAIL" value="2016"/></gen:Attributes></gen:Obs><gen:Obs><gen:ObsKey><gen:Value id="FREQ" value="A"/><gen:Value id="REPORTING_TYPE" value="N"/><gen:Value id="SERIES" value="_L_KG_170301_1A"/><gen:Value id="REF_AREA" value="KG"/><gen:Value id="ACTIVITY" value="ISIC4_N"/></gen:ObsKey><gen:ObsValue value="123.3"/><gen:Attributes><gen:Value id="UNIT_MEASURE" value="PER_1000_USD"/><gen:Value id="TIME_DETAIL" value="2017"/></gen:Attributes></gen:Obs><gen:Obs><gen:ObsKey><gen:Value id="FREQ" value="A"/><gen:Value id="REPORTING_TYPE" value="N"/><gen:Value id="SERIES" value="_L_KG_170301_1A"/><gen:Value id="REF_AREA" value="KG"/><gen:Value id="ACTIVITY" value="ISIC4_N"/></gen:ObsKey><gen:ObsValue value="76.1"/><gen:Attributes><gen:Value id="UNIT_MEASURE" value="PER_1000_USD"/><gen:Value id="TIME_DETAIL" value="2018"/></gen:Attributes></gen:Obs><gen:Obs><gen:ObsKey><gen:Value id="FREQ" value="A"/><gen:Value id="REPORTING_TYPE" value="N"/><gen:Value id="SERIES" value="_L_KG_170301_1A"/><gen:Value id="REF_AREA" value="KG"/><gen:Value id="ACTIVITY" value="ISIC4_P"/></gen:ObsKey><gen:ObsValue value="0.3"/><gen:Attributes><gen:Value id="UNIT_MEASURE" value="PER_1000_USD"/><gen:Value id="TIME_DETAIL" value="2008"/></gen:Attributes></gen:Obs><gen:Obs><gen:ObsKey><gen:Value id="FREQ" value="A"/><gen:Value id="REPORTING_TYPE" value="N"/><gen:Value id="SERIES" value="_L_KG_170301_1A"/><gen:Value id="REF_AREA" value="KG"/><gen:Value id="ACTIVITY" value="ISIC4_P"/></gen:ObsKey><gen:ObsValue value="139.3"/><gen:Attributes><gen:Value id="UNIT_MEASURE" value="PER_1000_USD"/><gen:Value id="TIME_DETAIL" value="2009"/></gen:Attributes></gen:Obs><gen:Obs><gen:ObsKey><gen:Value id="FREQ" value="A"/><gen:Value id="REPORTING_TYPE" value="N"/><gen:Value id="SERIES" value="_L_KG_170301_1A"/><gen:Value id="REF_AREA" value="KG"/><gen:Value id="ACTIVITY" value="ISIC4_P"/></gen:ObsKey><gen:ObsValue value="12.9"/><gen:Attributes><gen:Value id="UNIT_MEASURE" value="PER_1000_USD"/><gen:Value id="TIME_DETAIL" value="2010"/></gen:Attributes></gen:Obs><gen:Obs><gen:ObsKey><gen:Value id="FREQ" value="A"/><gen:Value id="REPORTING_TYPE" value="N"/><gen:Value id="SERIES" value="_L_KG_170301_1A"/><gen:Value id="REF_AREA" value="KG"/><gen:Value id="ACTIVITY" value="ISIC4_P"/></gen:ObsKey><gen:ObsValue value="5009.5"/><gen:Attributes><gen:Value id="UNIT_MEASURE" value="PER_1000_USD"/><gen:Value id="TIME_DETAIL" value="2013"/></gen:Attributes></gen:Obs><gen:Obs><gen:ObsKey><gen:Value id="FREQ" value="A"/><gen:Value id="REPORTING_TYPE" value="N"/><gen:Value id="SERIES" value="_L_KG_170301_1A"/><gen:Value id="REF_AREA" value="KG"/><gen:Value id="ACTIVITY" value="ISIC4_P"/></gen:ObsKey><gen:ObsValue value="11.7"/><gen:Attributes><gen:Value id="UNIT_MEASURE" value="PER_1000_USD"/><gen:Value id="TIME_DETAIL" value="2014"/></gen:Attributes></gen:Obs><gen:Obs><gen:ObsKey><gen:Value id="FREQ" value="A"/><gen:Value id="REPORTING_TYPE" value="N"/><gen:Value id="SERIES" value="_L_KG_170301_1A"/><gen:Value id="REF_AREA" value="KG"/><gen:Value id="ACTIVITY" value="ISIC4_P"/></gen:ObsKey><gen:ObsValue value="17.3"/><gen:Attributes><gen:Value id="UNIT_MEASURE" value="PER_1000_USD"/><gen:Value id="TIME_DETAIL" value="2015"/></gen:Attributes></gen:Obs><gen:Obs><gen:ObsKey><gen:Value id="FREQ" value="A"/><gen:Value id="REPORTING_TYPE" value="N"/><gen:Value id="SERIES" value="_L_KG_170301_1A"/><gen:Value id="REF_AREA" value="KG"/><gen:Value id="ACTIVITY" value="ISIC4_P"/></gen:ObsKey><gen:ObsValue value="5.2"/><gen:Attributes><gen:Value id="UNIT_MEASURE" value="PER_1000_USD"/><gen:Value id="TIME_DETAIL" value="2016"/></gen:Attributes></gen:Obs><gen:Obs><gen:ObsKey><gen:Value id="FREQ" value="A"/><gen:Value id="REPORTING_TYPE" value="N"/><gen:Value id="SERIES" value="_L_KG_170301_1A"/><gen:Value id="REF_AREA" value="KG"/><gen:Value id="ACTIVITY" value="ISIC4_P"/></gen:ObsKey><gen:ObsValue value="6.1"/><gen:Attributes><gen:Value id="UNIT_MEASURE" value="PER_1000_USD"/><gen:Value id="TIME_DETAIL" value="2017"/></gen:Attributes></gen:Obs><gen:Obs><gen:ObsKey><gen:Value id="FREQ" value="A"/><gen:Value id="REPORTING_TYPE" value="N"/><gen:Value id="SERIES" value="_L_KG_170301_1A"/><gen:Value id="REF_AREA" value="KG"/><gen:Value id="ACTIVITY" value="ISIC4_Q"/></gen:ObsKey><gen:ObsValue value="397.7"/><gen:Attributes><gen:Value id="UNIT_MEASURE" value="PER_1000_USD"/><gen:Value id="TIME_DETAIL" value="2008"/></gen:Attributes></gen:Obs><gen:Obs><gen:ObsKey><gen:Value id="FREQ" value="A"/><gen:Value id="REPORTING_TYPE" value="N"/><gen:Value id="SERIES" value="_L_KG_170301_1A"/><gen:Value id="REF_AREA" value="KG"/><gen:Value id="ACTIVITY" value="ISIC4_Q"/></gen:ObsKey><gen:ObsValue value="395.3"/><gen:Attributes><gen:Value id="UNIT_MEASURE" value="PER_1000_USD"/><gen:Value id="TIME_DETAIL" value="2009"/></gen:Attributes></gen:Obs><gen:Obs><gen:ObsKey><gen:Value id="FREQ" value="A"/><gen:Value id="REPORTING_TYPE" value="N"/><gen:Value id="SERIES" value="_L_KG_170301_1A"/><gen:Value id="REF_AREA" value="KG"/><gen:Value id="ACTIVITY" value="ISIC4_Q"/></gen:ObsKey><gen:ObsValue value="127.2"/><gen:Attributes><gen:Value id="UNIT_MEASURE" value="PER_1000_USD"/><gen:Value id="TIME_DETAIL" value="2012"/></gen:Attributes></gen:Obs><gen:Obs><gen:ObsKey><gen:Value id="FREQ" value="A"/><gen:Value id="REPORTING_TYPE" value="N"/><gen:Value id="SERIES" value="_L_KG_170301_1A"/><gen:Value id="REF_AREA" value="KG"/><gen:Value id="ACTIVITY" value="ISIC4_Q"/></gen:ObsKey><gen:ObsValue value="73.0"/><gen:Attributes><gen:Value id="UNIT_MEASURE" value="PER_1000_USD"/><gen:Value id="TIME_DETAIL" value="2017"/></gen:Attributes></gen:Obs><gen:Obs><gen:ObsKey><gen:Value id="FREQ" value="A"/><gen:Value id="REPORTING_TYPE" value="N"/><gen:Value id="SERIES" value="_L_KG_170301_1A"/><gen:Value id="REF_AREA" value="KG"/><gen:Value id="ACTIVITY" value="ISIC4_Q"/></gen:ObsKey><gen:ObsValue value="8.1"/><gen:Attributes><gen:Value id="UNIT_MEASURE" value="PER_1000_USD"/><gen:Value id="TIME_DETAIL" value="2018"/></gen:Attributes></gen:Obs><gen:Obs><gen:ObsKey><gen:Value id="FREQ" value="A"/><gen:Value id="REPORTING_TYPE" value="N"/><gen:Value id="SERIES" value="_L_KG_170301_1A"/><gen:Value id="REF_AREA" value="KG"/><gen:Value id="ACTIVITY" value="ISIC4_R"/></gen:ObsKey><gen:ObsValue value="37.0393"/><gen:Attributes><gen:Value id="UNIT_MEASURE" value="PER_1000_USD"/><gen:Value id="TIME_DETAIL" value="2008"/></gen:Attributes></gen:Obs><gen:Obs><gen:ObsKey><gen:Value id="FREQ" value="A"/><gen:Value id="REPORTING_TYPE" value="N"/><gen:Value id="SERIES" value="_L_KG_170301_1A"/><gen:Value id="REF_AREA" value="KG"/><gen:Value id="ACTIVITY" value="ISIC4_R"/></gen:ObsKey><gen:ObsValue value="476.6"/><gen:Attributes><gen:Value id="UNIT_MEASURE" value="PER_1000_USD"/><gen:Value id="TIME_DETAIL" value="2009"/></gen:Attributes></gen:Obs><gen:Obs><gen:ObsKey><gen:Value id="FREQ" value="A"/><gen:Value id="REPORTING_TYPE" value="N"/><gen:Value id="SERIES" value="_L_KG_170301_1A"/><gen:Value id="REF_AREA" value="KG"/><gen:Value id="ACTIVITY" value="ISIC4_R"/></gen:ObsKey><gen:ObsValue value="33.1"/><gen:Attributes><gen:Value id="UNIT_MEASURE" value="PER_1000_USD"/><gen:Value id="TIME_DETAIL" value="2011"/></gen:Attributes></gen:Obs><gen:Obs><gen:ObsKey><gen:Value id="FREQ" value="A"/><gen:Value id="REPORTING_TYPE" value="N"/><gen:Value id="SERIES" value="_L_KG_170301_1A"/><gen:Value id="REF_AREA" value="KG"/><gen:Value id="ACTIVITY" value="ISIC4_R"/></gen:ObsKey><gen:ObsValue value="141.5"/><gen:Attributes><gen:Value id="UNIT_MEASURE" value="PER_1000_USD"/><gen:Value id="TIME_DETAIL" value="2012"/></gen:Attributes></gen:Obs><gen:Obs><gen:ObsKey><gen:Value id="FREQ" value="A"/><gen:Value id="REPORTING_TYPE" value="N"/><gen:Value id="SERIES" value="_L_KG_170301_1A"/><gen:Value id="REF_AREA" value="KG"/><gen:Value id="ACTIVITY" value="ISIC4_R"/></gen:ObsKey><gen:ObsValue value="240.4"/><gen:Attributes><gen:Value id="UNIT_MEASURE" value="PER_1000_USD"/><gen:Value id="TIME_DETAIL" value="2013"/></gen:Attributes></gen:Obs><gen:Obs><gen:ObsKey><gen:Value id="FREQ" value="A"/><gen:Value id="REPORTING_TYPE" value="N"/><gen:Value id="SERIES" value="_L_KG_170301_1A"/><gen:Value id="REF_AREA" value="KG"/><gen:Value id="ACTIVITY" value="ISIC4_R"/></gen:ObsKey><gen:ObsValue value="4712.0"/><gen:Attributes><gen:Value id="UNIT_MEASURE" value="PER_1000_USD"/><gen:Value id="TIME_DETAIL" value="2017"/></gen:Attributes></gen:Obs><gen:Obs><gen:ObsKey><gen:Value id="FREQ" value="A"/><gen:Value id="REPORTING_TYPE" value="N"/><gen:Value id="SERIES" value="_L_KG_170301_1A"/><gen:Value id="REF_AREA" value="KG"/><gen:Value id="ACTIVITY" value="ISIC4_S"/></gen:ObsKey><gen:ObsValue value="0.1"/><gen:Attributes><gen:Value id="UNIT_MEASURE" value="PER_1000_USD"/><gen:Value id="TIME_DETAIL" value="2013"/></gen:Attributes></gen:Obs><gen:Obs><gen:ObsKey><gen:Value id="FREQ" value="A"/><gen:Value id="REPORTING_TYPE" value="N"/><gen:Value id="SERIES" value="_L_KG_170301_1A"/><gen:Value id="REF_AREA" value="KG"/><gen:Value id="ACTIVITY" value="ISIC4_S"/></gen:ObsKey><gen:ObsValue value="50.4"/><gen:Attributes><gen:Value id="UNIT_MEASURE" value="PER_1000_USD"/><gen:Value id="TIME_DETAIL" value="2018"/></gen:Attributes></gen:Obs></mes:DataSet></mes:GenericData>