[{"Year":"2007","Value":6.1,"Series":"Number of commercial bank branches per 100,000 adults"},{"Year":"2008","Value":6.5,"Series":"Number of commercial bank branches per 100,000 adults"},{"Year":"2009","Value":6.6,"Series":"Number of commercial bank branches per 100,000 adults"},{"Year":"2010","Value":5.7,"Series":"Number of commercial bank branches per 100,000 adults"},{"Year":"2011","Value":6.8,"Series":"Number of commercial bank branches per 100,000 adults"},{"Year":"2012","Value":7.3,"Series":"Number of commercial bank branches per 100,000 adults"},{"Year":"2013","Value":7.4,"Series":"Number of commercial bank branches per 100,000 adults"},{"Year":"2014","Value":7.4,"Series":"Number of commercial bank branches per 100,000 adults"},{"Year":"2015","Value":7.8,"Series":"Number of commercial bank branches per 100,000 adults"},{"Year":"2016","Value":7.9,"Series":"Number of commercial bank branches per 100,000 adults"},{"Year":"2017","Value":7.7,"Series":"Number of commercial bank branches per 100,000 adults"},{"Year":"2018","Value":7.6,"Series":"Number of commercial bank branches per 100,000 adults"},{"Year":"2007","Value":2.5,"Series":"Number of automated teller machines (ATMs) per 100,000 adults"},{"Year":"2008","Value":4.9,"Series":"Number of automated teller machines (ATMs) per 100,000 adults"},{"Year":"2009","Value":8.7,"Series":"Number of automated teller machines (ATMs) per 100,000 adults"},{"Year":"2010","Value":7.6,"Series":"Number of automated teller machines (ATMs) per 100,000 adults"},{"Year":"2011","Value":12.3,"Series":"Number of automated teller machines (ATMs) per 100,000 adults"},{"Year":"2012","Value":160.0,"Series":"Number of automated teller machines (ATMs) per 100,000 adults"},{"Year":"2013","Value":21.1,"Series":"Number of automated teller machines (ATMs) per 100,000 adults"},{"Year":"2014","Value":25.3,"Series":"Number of automated teller machines (ATMs) per 100,000 adults"},{"Year":"2015","Value":30.8,"Series":"Number of automated teller machines (ATMs) per 100,000 adults"},{"Year":"2016","Value":31.9,"Series":"Number of automated teller machines (ATMs) per 100,000 adults"},{"Year":"2017","Value":34.2,"Series":"Number of automated teller machines (ATMs) per 100,000 adults"},{"Year":"2018","Value":37.7,"Series":"Number of automated teller machines (ATMs) per 100,000 adults"}]