{"data":{"Year":["2018","2018","2018","2018","2018","2018","2018","2018","2018","2018","2018","2018"],"Observation status":["Normal value","Normal value","Normal value","Normal value","Normal value","Normal value","Normal value","Normal value","Normal value","Normal value","Normal value","Normal value"],"Unit multiplier":["Units","Units","Units","Units","Units","Units","Units","Units","Units","Units","Units","Units"],"Nature of data points":["Country Data","Country Data","Country Data","Country Data","Country Data","Country Data","Country Data","Country Data","Country Data","Country Data","Country Data","Country Data"],"Source details":["\u041f\u043e \u0434\u0430\u043d\u043d\u044b\u043c \u041a\u041e\u041c\u041f 2018","\u041f\u043e \u0434\u0430\u043d\u043d\u044b\u043c \u041a\u041e\u041c\u041f 2018","\u041f\u043e \u0434\u0430\u043d\u043d\u044b\u043c \u041a\u041e\u041c\u041f 2018","\u041f\u043e \u0434\u0430\u043d\u043d\u044b\u043c \u041a\u041e\u041c\u041f 2018","\u041f\u043e \u0434\u0430\u043d\u043d\u044b\u043c \u041a\u041e\u041c\u041f 2018","\u041f\u043e \u0434\u0430\u043d\u043d\u044b\u043c \u041a\u041e\u041c\u041f 2018","\u041f\u043e \u0434\u0430\u043d\u043d\u044b\u043c \u041a\u041e\u041c\u041f 2018","\u041f\u043e \u0434\u0430\u043d\u043d\u044b\u043c \u041a\u041e\u041c\u041f 2018","\u041f\u043e \u0434\u0430\u043d\u043d\u044b\u043c \u041a\u041e\u041c\u041f 2018","\u041f\u043e \u0434\u0430\u043d\u043d\u044b\u043c \u041a\u041e\u041c\u041f 2018","\u041f\u043e \u0434\u0430\u043d\u043d\u044b\u043c \u041a\u041e\u041c\u041f 2018","\u041f\u043e \u0434\u0430\u043d\u043d\u044b\u043c \u041a\u041e\u041c\u041f 2018"],"Frequency of observation":["Annual","Annual","Annual","Annual","Annual","Annual","Annual","Annual","Annual","Annual","Annual","Annual"],"Reporting type":["National","National","National","National","National","National","National","National","National","National","National","National"],"Series":["_L_KG_050601_1","_L_KG_050601_1","_L_KG_050601_1","_L_KG_050601_1","_L_KG_050601_1","_L_KG_050601_1","_L_KG_050601_1","_L_KG_050601_1","_L_KG_050601_1","_L_KG_050601_1","_L_KG_050601_1","_L_KG_050601_1"],"Reference area":[null,null,null,"Batken","Jalal-Abad","Issyk-Kul","Naryn","Osh","Talas","Chui","Bishkek (city)","Osh (city)"],"Sex":["Female","Female","Female","Female","Female","Female","Female","Female","Female","Female","Female","Female"],"Age":["15 to 49 years old","15 to 49 years old","15 to 49 years old","15 to 49 years old","15 to 49 years old","15 to 49 years old","15 to 49 years old","15 to 49 years old","15 to 49 years old","15 to 49 years old","15 to 49 years old","15 to 49 years old"],"Degree of urbanisation":[null,"Urban","Rural",null,null,null,null,null,null,null,null,null],"Units":["PT","PT","PT","PT","PT","PT","PT","PT","PT","PT","PT","PT"],"Value":[99.7,99.8,99.6,99.7,99.4,100.0,99.7,99.8,100.0,99.5,99.9,99.5]},"edges":{"From":["Nature of data points","Source details","Frequency of observation","Reporting type","Age","Sex","Age"],"To":["Source details","Frequency of observation","Reporting type","Sex","Reference area","Age","Degree of urbanisation"]}}