{"Year":["2010","2011","2012","2013","2014","2015","2016","2017","2018"],"concept.FREQ":["CL_FREQ.A","CL_FREQ.A","CL_FREQ.A","CL_FREQ.A","CL_FREQ.A","CL_FREQ.A","CL_FREQ.A","CL_FREQ.A","CL_FREQ.A"],"concept.REPORTING_TYPE":["CL_REPORTING_TYPE.N","CL_REPORTING_TYPE.N","CL_REPORTING_TYPE.N","CL_REPORTING_TYPE.N","CL_REPORTING_TYPE.N","CL_REPORTING_TYPE.N","CL_REPORTING_TYPE.N","CL_REPORTING_TYPE.N","CL_REPORTING_TYPE.N"],"Series":["CL_SERIES.SL_EMP_GTOTL","CL_SERIES.SL_EMP_GTOTL","CL_SERIES.SL_EMP_GTOTL","CL_SERIES.SL_EMP_GTOTL","CL_SERIES.SL_EMP_GTOTL","CL_SERIES.SL_EMP_GTOTL","CL_SERIES.SL_EMP_GTOTL","CL_SERIES.SL_EMP_GTOTL","CL_SERIES.SL_EMP_GTOTL"],"concept.REF_AREA":["CL_AREA.KG","CL_AREA.KG","CL_AREA.KG","CL_AREA.KG","CL_AREA.KG","CL_AREA.KG","CL_AREA.KG","CL_AREA.KG","CL_AREA.KG"],"Units":["CL_UNIT_MEASURE.PT","CL_UNIT_MEASURE.PT","CL_UNIT_MEASURE.PT","CL_UNIT_MEASURE.PT","CL_UNIT_MEASURE.PT","CL_UNIT_MEASURE.PT","CL_UNIT_MEASURE.PT","CL_UNIT_MEASURE.PT","CL_UNIT_MEASURE.PT"],"Value":[29.6,29.0,30.0,28.3,26.8,27.0,28.4,26.8,29.4]}